{"iso3":"BLZ","sources":{"uk":[{"h":"Before you travel","s":["f80df97a90","1247745177","d466f7d831"]},{"h":"Travel insurance","s":["f7bca95a22","d525b49a56"]},{"h":"About FCDO travel advice","s":["26ddbb36bc","2fcfafd29c"]},{"h":"Get travel advice updates","s":["35178cefc0","0642c06b73","8531074422"]},{"h":"Entry requirements","s":["06da9c5f36","ec7121f2dc","8902f0bffa","c0d14feeca"]},{"h":"Passport validity requirements","s":["ba1cee6b50","f0e4ac1da7","1425eaa9df","5d8ec4d006","89f00503d4"]},{"h":"Dual nationals","s":["88479bad5e"]},{"h":"Immigration and customs declaration form","s":["91626d309f","2338283b3d"]},{"h":"Visa requirements","s":["6f3c7cf0a6","01d2b90deb","89eee7d8c8"]},{"h":"Departure tax","s":["3bf2e8c7d8","a635f4075d"]},{"h":"Travelling with children","s":["9f5aaef285","fa9d2703b1"]},{"h":"Vaccine requirements","s":["bc5e638713"]},{"h":"Customs rules","s":["a7411add41","13e16ed773","0585902063","97d86bc455"]},{"h":"Terrorism","s":["00c5716f55","cb2e68f5c1","5d7de7e864","b7d161f0e6"]},{"h":"Terrorism in Belize","s":["d4ace9ece4"]},{"h":"Political situation","s":["519b9a0d3d","ac0b033418"]},{"h":"Crime","s":["f59dec54f9","5b36470398","5d5a6efea7","ea40547e9e","dc1d30d4ad","a81fdc944d","850bcf3c07","b1fb01bdb7","ea16b43f8e"]},{"h":"Illegal drugs and prison sentences","s":["0132f9aec0"]},{"h":"LGBT+ travellers","s":["30e38d651f","ba0b167072","193e7dfab1","476f7bae67","1b9a2e45a4"]},{"h":"Outdoor activities and adventure tourism","s":["dcf4cf5282"]},{"h":"Swimming safety","s":["7afd6f15a1","84ce52a4a1","6717e117e9","8c8fcd0342"]},{"h":"Road travel","s":["6c8d8d40a1","2613b247a5","5760b4eedd","f37e274b2c","5d72bedf93"]},{"h":"Driving standards","s":["52ecfb8ddb","f8cf9312f8","16a5aa4f35","344b18ad59","5365eaad18"]},{"h":"Taxis","s":["4887d33d15","2d06e84242"]},{"h":"Air Travel","s":["2ff25b66bf","99ae99f083"]},{"h":"Extreme weather and natural disasters","s":["7b3f982348"]},{"h":"Hurricanes","s":["c80a1e3f9d","18d100179e","b7ba749c2e"]},{"h":"Flooding","s":["8d007049a9","ef311f75e0","e505464486","a53b5006c5"]},{"h":"Earthquakes","s":["1ef2522071","a614e3aedd","d4500de134"]},{"h":"Health","s":["ea1848d96e"]},{"h":"Emergency medical number","s":["8597f47f62","9aae05ed42"]},{"h":"Vaccine recommendations and health risks","s":["ad2aabc59e"]},{"h":"Medication","s":["0b9698c3cc","e271b00145"]},{"h":"Healthcare in Belize","s":["85c6ad8611","2e45136631","a0e1b03520","81d415bf3e"]},{"h":"Travel and mental health","s":["2673c32602","df5b1cc876"]},{"h":"Getting help","s":["9486662c5c","fcbf9dc697"]},{"h":"Emergency services in Belize","s":["5b435a2609"]},{"h":"Contact your travel provider and insurer","s":["50a956fd66","b8a040f875"]},{"h":"Refunds and changes to travel","s":["0c45bee965","63b153d907","72ccd48e09","52ac5911c3"]},{"h":"Support from FCDO","s":["4415a54f36"]},{"h":"Help abroad","s":["2606726f78"]},{"h":"Help in the UK","s":["c91e1e7bcf","2cb12c389a"]}],"ca":[{"h":"Risk level","s":["c53b3216a4","5eeb6bc4d5","3b9872f5c5","6011e943c2"]},{"h":"Belize travel advice","s":["c53b3216a4","5eeb6bc4d5","3b9872f5c5","6011e943c2"]},{"h":"Belize - Exercise a high degree of caution","s":["ba3c8520ad"]},{"h":"Southside Belize City - Avoid non-essential travel","s":["eac73f53dc"]},{"h":"Southside Belize City","s":["1c4a2da4dd","47bb84c8f0","046d9eea78","416277d894","ab0f0e7446"]},{"h":"Violent crime","s":["ea602fc4b4","bd1730e10b","d53a4e6ab8","ef2195bc92","33c60948b2","6791f68afc"]},{"h":"Petty crime","s":["6a02256d9c","eadc4d6b37","7c3e8d4d2e","3d74133bc2"]},{"h":"Border areas","s":["a24b7a4d6c","5e22f4fae2","3b598cfb05"]},{"h":"Fraud","s":["cf72b2bc06","7c10926b62"]},{"h":"Spiked food, drinks and other items","s":["78da5b043f","5e8ae80b0e"]},{"h":"Women’s safety","s":["de236087b4","2bff621ac7","1847fa0d9e","fdd92838cf"]},{"h":"2SLGBTQI+ persons","s":["f310a2a372","c6a479230a","15858335c6","98a2b96ece","c8389dc3a5","aee3606228"]},{"h":"Demonstrations","s":["4b82b093b6","273cc2fde2","a5925cde32","31039192ed"]},{"h":"Water activities","s":["b06149a404","cbfbaf6f5f","6e088868be","c24e7be147"]},{"h":"Adventure travel","s":["1ca6bad29f","4ee4b29593","21f1a5168b"]},{"h":"Road safety","s":["9e1e10c0dd","a91542420d"]},{"h":"Road conditions","s":["b30f1cc0d6","e2f2ecd2b9","f057f56e28","886c179e01","981a59d5e3"]},{"h":"Driving habits","s":["563d3b16a8","7cb0f0ec8e","76d84a5119","47954ba226","0e1083762e"]},{"h":"Buses","s":["571d6dd5e8","e6b7d61b1b"]},{"h":"Taxis","s":["6d494e3ebc","2bbee9d13f","f157de2eb6"]},{"h":"Ferries and water taxis","s":["060688458b","809e7cc0bc"]},{"h":"Air travel","s":["618ff0158b","737f618423"]},{"h":"Entry and exit requirements","s":["c809de2214","0c4f7e6a86","4a858ff1be","4a5b281771","7ed138dba0","d01d48175d","33da193a55","eab79dcc9e","b1623e326a"]},{"h":"Passport","s":["a9fd2c2092","85fd51d046","2b4f7eec44"]},{"h":"Regular Canadian passport","s":["86c85ed719"]},{"h":"Passport for official travel","s":["5e13493cdb"]},{"h":"Passport with “X” gender identifier","s":["a5d0d22e7f","3a9e8e0967","96fd38f9c0","472df9c850","06bc47c6d5"]},{"h":"Other travel documents","s":["ba1a531323","96fd38f9c0"]},{"h":"Useful links","s":["a770800db2","55f3f12ad7","7152631b49","7c614ac66e","fc4498d102"]},{"h":"Visas","s":["cdfa062b46","140572cd15","4694201e0f"]},{"h":"Travel declaration form","s":["d76f44403f","9eec9ae46a","2409234023"]},{"h":"Other entry requirements","s":["1a899e6259"]},{"h":"Children and travel","s":["6f6b9cfe5d"]},{"h":"Yellow fever","s":["e0529db33c"]},{"h":"Relevant Travel Health Notices","s":["3f673a67e8","7e9fc01a71","750a1108ea","6ea132f448","83082c45eb"]},{"h":"Routine vaccines","s":["500994dc13","ab29ea7380","ae26ea404a"]},{"h":"Pre-travel vaccines and medications","s":["2c88a09be2","3ad680fa3d","1d71c13dd2","37bf6c905d","a4cdcc722b","ad9fe58e37","3677c4c6fd","64a6728129","5d1e6bd3ee","6d280f4f1d","bd517010b7","48c901c801","a4c7ace92c","4a759c89be","81d04d5165","1a546de403","75364f3d25","9ed8c5e4b5","4b15c4f04b","d24b90baf6","d8d2cb513b","26be41713b","512f34c603","57ac39b68f","8dbc1913c9","78f32974cc","c014cd8779","750338ae5a","fc52bcc6e1","1ae555a22f","3270c4f15b","5d5efcebe3","7cad06eb71","9652a96b60","6d86ff4a63","7d2e0c728d","9e256a1a4d","8c5a556c39","388a7e17f1","8c848e5a42","d90ecf381b","78c642d005","fcebf2f5d3","efc1c9423c","042ecf5010","c13e057c28","5f61850252","d7fa46425f","d15609e155","027b211896"]},{"h":"Safe food and water precautions","s":["ac6e4fe273","caa8724e5c","9414eaf8c8","28b068531c","61143e885c","6568a62f16","28f9111409","fdf4d47641","dff827b0f9","4b35ac3730"]},{"h":"Tick and insect bite prevention","s":["8183637a01","1e1be6885e","d4f7ecdd80","d395807060","a52ec8c4c0","1daec042fa","0437d8e719","a2b31e3b8e","11acb026db","e41b5bdde2","20eb3aa470","fc48bee7a0","9cf5ddf12a","9b209f883f","2382f798a8","998959c9c6","48cead78eb","2e22d99ff0","678e005abd","861192d8b9","7c1fbe1962","b43c162695","a97faad1f6","7cb5fc218c","b2f21b0650","c434d13691","8e84707cfd","b7de9306de","df27bd5e46","797a6cc8f9","235011eeb1","cea823ae18","d8d12bfe24"]},{"h":"Animal precautions","s":["8996d01ae3","a41bebf7d2","ac7a7635ac","09c2126a3b"]},{"h":"Person-to-person infections","s":["3358dcd377","8d01286122"]},{"h":"Medical services and facilities","s":["c2ea30a3d3","d293842b83","4113e25e74","a841890280","dd7355a2f2","6b3a06c7c6","ac4dbd4b06","664646af20","7179eef940","a7d6c69b06","9a685538e4"]},{"h":"Medication","s":["0f6290c1e0","d79235dd02"]},{"h":"Keep in Mind...","s":["bdb49a1fb7","073438819a","5b61356078","af6d2355fb"]},{"h":"Laws and culture","s":["11b7256cb8","4cc2713baf"]},{"h":"Transfer to a Canadian prison","s":["8bfc985438","d9d082c62e","6891343964","d357b16575","cd7133cb81","d06fe653d5"]},{"h":"Death penalty","s":["6aab86c948"]},{"h":"Drugs","s":["518f4bd45f","583b683b77","12bb35e9ec","ef375df25f"]},{"h":"Firearms","s":["1e6907bd45","a4c03b505a"]},{"h":"Artifacts","s":["573421bad1","49aac237a4"]},{"h":"Plants, animals and animal products","s":["f1d9502845","4fba7018af"]},{"h":"Investments","s":["0c6dd150b5","961eabeadd","4f51f076a5"]},{"h":"Dual citizenship","s":["a8df0ceadf","a2808dd0f2","4af3a7d11b"]},{"h":"International Child Abduction","s":["7ba2b3816c","5ca3de5726","934c9a2b54","258addbec7","c9a31ce7d7","a12f2ecde4"]},{"h":"Identification","s":["ce034d517a","c5df926e20","f1587b0379"]},{"h":"Recreational boating","s":["b17233d48b","e708161dfb","629fd978b9","0c76560469"]},{"h":"Driving","s":["4f602a6687","a9d8524722","139fbd5709"]},{"h":"Money","s":["87ac6620bc","b7cdd337f4","4d356e68e1","c2a2be2eb8","0bcd43c325","c8a4ddae6a","1c74131d60","bc1d67d71f"]},{"h":"Hurricane season","s":["9cd79083bc","8bb56ed1d0","9b20f04494","8d1c158eed","406cee45cd","10de609e93"]},{"h":"Rainy season","s":["2228563c08","b01c095331","c60c3ec2f5","c06099b500"]},{"h":"Wildfires","s":["ee7aa9877a","9b6a19affa","304a91d8d5"]},{"h":"Local services","s":["12a1821e4c"]},{"h":"Consular assistance","s":["ef6b2b034e","4caad08dd6","66ba13ab81"]},{"h":"Disclaimer","s":["8c982efbce","296a10ebaa","8ea9567a5d","9d5517f3d6","4c66eb963c","777d582203","958465c72a","de8fb4c067"]},{"h":"Take normal security precautions","s":["e1d8cf294b"]},{"h":"Exercise a high degree of caution","s":["754555669f","f57d43f561","8171dadf9f"]},{"h":"Avoid non-essential travel","s":["3a230c5c6f","79fddc8d7d","f58fb693fc","1126e35f73"]},{"h":"Avoid all travel","s":["889fe83dc7","1f4024f324","484c8ff5ca","e2aa6bfba1"]}],"ie":[{"h":"Get travel and medical insurance","s":["39ad97923a","2a7d9532e3"]},{"h":"General Travel Advice","s":["04f27cf813","140572cd15","e313c2644f","d57a178c37","4324bbecd7","3eef1faa17","8ec6073a3b","554927237b","2acdb50fd1"]},{"h":"Emergency Assistance","s":["9653f29eda","446030e6a7"]},{"h":"Our tips for Safe Travels:","s":["a8a3740a36","0bee27b14a","e374cacd95","54b95c12c9","2d811077a3","ebf8ce831a","2ff5c6534d"]},{"h":"Safety and Security","s":["3a3d541e34","4384fbc9c0","296877bd34","03fc919453","fe2bce5021","ef251d6c24","6db3172b99","ec4d45857f","ce62520bc2","0d3ebe7fa7","d0620d2ed4","53a00c4358","e4f0ea1c26","f2c7224302","873fc41fb1","fdf60b7ed9","b323e5a4e0","20e82aa428","647ef3ea63","5bd3d6ffdd"]},{"h":"Local Laws and Customs","s":["ad195fee3d","e17bb424de","42437ca72c","2ff691c392","c60b463623","84a0a025e2"]},{"h":"Health","s":["1d96eb561d","50711b55a5","c0b88f47cf","874a8d6b6b","ada998a79e","37db7287b7","6bcfefcd5f","769d74bec9"]},{"h":"Additional information","s":["294265e493","50b0a4ed57","91be45ef5e","3b48c42053","bb81352f8d","d57a178c37","bc6305d900"]},{"h":"Embassy contact","s":["31bcab7977","ac762e64d9","f638324cd4"]}],"fr":[{"h":"Hausse des cas de rougeole","s":["61ba280b93"]},{"h":"Découvrez notre podcast : Sources diplomatiques","s":["642b6240a2"]},{"h":"Suivez-nous sur les réseaux sociaux","s":["0fe4a58127"]}],"au":[{"h":"Latest update","s":["73267dbd07","08cbc2a860","873fc677fc"]},{"h":"Local emergency contacts","s":["8aa31ffac8","28fffba1b1","d10fc3009b","6711a6c58a","73267dbd07","3168f4f408"]},{"h":"Safety","s":["0c87567712","c07ec35a0b","fa319892d1","7b11141fcc","7957b72971","42290eaaa8","1e20d87895"]},{"h":"Health","s":["61ad94ff61","459f43b73c","07127dcfda","477a8a3154","0b12b7f275","01169a2aa3","c9b88465d0","f11a3e265f","65488ab3da","a21c620c88","9891072e0f"]},{"h":"Local laws","s":["281ad9ff36","d365547c78","65f3ea61e2","c94abf8678","dafe6a73a7","cbb6b2f90a","e4d7ae9842","4d5d4dd4e1","d47dc952a7"]},{"h":"Travel","s":["55feec347e","6240d3afe0","7346ba2a5e","1ba701289b","8717c90c00","8d222efa97","b7c5c44f4d","a0c007f999","f20b63a9d9"]},{"h":"Local contacts","s":["2a59b0e052","1c90bebae1","db1b20c814","a5bbd84a47","f17ff9087b","06ab174f54","c63e03524b"]},{"h":"Violent crime","s":["40e59c5a6e","c84a6ff3ab","47bb84c8f0","046d9eea78","fd8e3cd91d","416277d894","8a0b4ab185","eefaff1aa7","0c0c54e49f","3e7f12ddcc","5332f7a8c8","dda6ade73a"]},{"h":"Petty Crime","s":["dda8e396f4","8c871ee4cf"]},{"h":"Kidnapping","s":["0fff691c73","d6063daaf0","d6932acd9d"]},{"h":"Civil unrest and political tension","s":["cfdb1447cb","ab0d8ae054"]},{"h":"Terrorism","s":["437889ef8f","8e9e321b77","2aa2d23adc","f7e70e8fa7","b7b50f643f"]},{"h":"Tours","s":["2c096af87a","19c9a1084d","a01f318649"]},{"h":"Extreme weather and natural disasters","s":["d39db47b73","b1edd8b545","a7aaf69bc5","06b1c56f9d","49cce91303"]},{"h":"Hurricanes and severe weather","s":["0b365f71ac","f589371f92","5a6bcd7f99","618bda2293","dfc10f1d12","c614189219","8c961fce51","c1f58b0a7e","8c36d98fca"]},{"h":"Earthquakes and tsunamis","s":["abb099a52a","06e4caa99d","36cb6077ca","a352e37744","7ae4901061"]},{"h":"Travel insurance","s":["cca83e0a99","0603d7fb9f","0386d91c87","9f25331b45","0049563c77","e111f08d0c","5f708b0ebe","15464d9e98"]},{"h":"Physical and mental health","s":["5d4aba9644","21ccd56bfe","f538a1d44b","9998152d6f","1fd09c5863","590f61a23d","62f53aa831"]},{"h":"Insect-borne diseases","s":["a96b4cbbcf","9b0ca3da12","1eedcc660c","cb7d846fe5","210de35336"]},{"h":"Other health risks","s":["f11a3e265f","f90887b58d","12ec669094","aac387cf8f"]},{"h":"Medical care","s":["c909c940d9","cf330e811d","af7faa1e50","b71959f43b","826362edbf","f36d74e93a"]},{"h":"Drugs","s":["376c04801c","082e713916","da2b33d45e","41baa5d8f9","841375c217"]},{"h":"LGBTQIA+ laws","s":["04f1d2fe29","cbb6b2f90a","2909c9168d","9c51e32c47","b6cb80220a"]},{"h":"Visas and border measures","s":["49722fec03","4bab967729","0408c5be48","05c634d94d","c07ec35a0b","1ba701289b","5ec2fa9b06","8d222efa97"]},{"h":"Tourist visas","s":["2105f7bf93","c36b608d3b","f9398a35b4","fbf0ed40f0","0f50910c20"]},{"h":"Travel via the United States","s":["70dd97bd3a","195265556b"]},{"h":"Yellow fever vaccination","s":["a98d671e7d","fb1738eb57","0d3f5f3adf","ae082be205"]},{"h":"Lost or stolen passport","s":["d156aaaac2","0da0b9f75f","2844cfb56f","585aa228c2","e7c9b04aac"]},{"h":"Passport with ‘X’ gender identifier","s":["5a7fc752e7","a2d5aef02c","3d476af809","f936adf1e5","b6cb80220a"]},{"h":"Money","s":["e1ac6ca1af","47f13a4152","2195e92a1b","e8ecc5f108","54fb9a101e","d0d9a7b3d9"]},{"h":"Local travel","s":["7845c8406e","f15596ae03","09a6fc8474"]},{"h":"Driving permit","s":["20e62e35d8","35ecaef00c","8777900a89","9b8eea24f4"]},{"h":"Road travel","s":["bcd5d4e315","de43e99f9a","b79508055f","839e8fcaf7","cf528c9002","044eba71c3","5745b2d91c"]},{"h":"Motorcycles","s":["b612114901","89c45dabfe"]},{"h":"Taxis","s":["67a125a156","ad117a54f0","064c862e46"]},{"h":"Public transport","s":["c1cb046cab","bbf5d283ba","c014c67d21"]},{"h":"Sea Travel","s":["9f701230c6","4817ce8a48","64291aef15","9c1ed92126","0e6872a9b1"]},{"h":"Air travel","s":["a558aabf3a","b7f1c40b6a","2091249315","5a5356046b","df66b7c7a6","6f7e74c7d1","0477a72cfa","250a890013"]},{"h":"Consular contacts","s":["2a59b0e052","1c90bebae1","db1b20c814","b46a154ae4","f17ff9087b"]},{"h":"24-hour Consular Emergency Centre","s":["01b79befd6"]}],"es":[{"h":"Notas importantes","s":["dd0252fc06","fa91a021c0","fd5f3f5e5e","4b850d39ae","8b2c7b8546","a608968b0f"]},{"h":"Documentación y visados","s":["84587e3991","0248201069","55a03e0b91","f3b7655261","b2b08c882d","0b5826f04e","e0ece28854","080311ee2c","b31dc19ded","19d428683d","116851c8c9","fe450a9d44"]},{"h":"Seguridad","s":["aaeb1b1e11","b9efba7774","44748dbc56","dada46462f","68bd182ad1","c5f387bd3b","4917fd282b","7c720ef52d","b4e09f601b","fccba4d1e2","17c62a7d18","c960db8205","9982cecae9","b86e542fd4","ff8c23c838","22c5eab0ac","d47d5b4091","b6e5a16002","74c3dcede0","c0e165e050","64e7204e9b"]},{"h":"Sanidad","s":["6f62b02f71","8d54ad7201","e28089f8ce","dd8225ac92","f66a1230b8","40b8e5b5ba","898a93b0c5","73c4f04d06","7cd8e5de1c","10532f7bab","40db5b3fcb","a828ceecc6","cc535bab30","2dfeb7d4c3","d270cc00db","7ef106e98f","5a267680cd","af9b98b1ae","29a03d0c46","af8ba84184","118633dbe7","387af80472","ad6a1abc8e","d7c8a8e82b"]},{"h":"Divisas","s":["797a7e9c45","2bd4514f8a","c8250973a9","f047b51678"]},{"h":"Otros","s":["3f5f01e196","0515a680e0","0dccfb0134","c9621ccb54","07876b4546","31c639a8b8","48f37ba8dd","01c83f5187","d2e0ca773b","da8791db0e","769be9dc46","081d9b0a5f","b50906d1af","8e234096ef","1aa947ca36","7078532b0d","980ec75798","4c72879592","9f083accd3","6a0400379b","87467e5249","80975f4c19","f9fce7dd52","4daa4674ba","c91be39c95","f121a5f793","661dc3d037","43e02944d2","ec185bdc9f","cb3670a935","2b0f5880bb","c7d6052dfe","d418207eb0","5244097c8b","7155e7f3a6","ebf1e4c3b8","ae779e63ee","4bd9a62bf0","b47581ab40","96c7a4fc53","f5f519ffdd","2a1c60878a","3c3ca55bc1","87d940f4e4","42be5f5c07","4461b66545","fdf4b183bd"]},{"h":"Direcciones y teléfonos de interés","s":["f06ea46037","7e92b9c349","b8c3b0656a","d4dfd43c3f","44cf3beba3","ed472185b6"]}]}}