{"generatedAt":"2026-07-15T07:31:51.806Z","countries":226,"terms":{"kameraovervagning":["DEU"],"kanada":["AZE","CAN","DEU","GEO","HTI","IRN","MEX","PAN","TTO","TUR","USA"],"karneval":["DEU","TTO"],"katwarn":["DEU"],"keeping":["AIA","AUS","BDI","BHS","CAF","CAN","COG","CPV","CUB","CUW","DEU","DJI","DOM","ERI","GAB","GIN","GRC","GTM","HND","LAO","LKA","MEX","MLT","MOZ","MUS","MWI","NGA","OMN","PNG","PRT","SEN","SLV","STP","TLS","TTO","VCT","YEM","ZMB"],"kemisk":["DEU","FRA","GRC","POL","SWE"],"kirke":["AUS","BEL","CAN","CHN","DEU","ESP","GBR","ISR","ITA","MYS","NOR","PHL","RUS","SGP","SWE","THA","TUR","USA"],"knife":["AUT","BDI","BFA","BRA","CHN","DEU","ECU","FRA","GBR","GRC","ISL","JOR","MDV","SWE","TUN"],"knivangreb":["DEU","FRA","ISR"],"knive":["BRA","CHL","CRI","DEU","ECU","ETH","GBR","GEO","GTM","GUY","HND","KHM","KIR","LAO","LBR","MAR","MEX","MOZ","PNG","SLV","TLS","TUR","VNM"],"kortet":["BEL","BGR","CZE","DEU","ESP","EST","FIN","FRA","GBR","GRC","HRV","HUN","IRL","ISL","ITA","LTU","LVA","NOR","POL","PRT","SWE"],"kriminelle":["BIH","BRA","CAN","CHL","CHN","CMR","COD","COL","DEU","DJI","DZA","ECU","ESP","FRA","GHA","HTI","IND","ISR","JOR","KEN","KGZ","KHM","LAO","MAR","MEX","MMR","MRT","MYS","NAM","NGA","NPL","PAK","PAN","PER","PHL","PRT","RWA","SAU","SDN","SEN","SSD","SYR","THA","TUR","UGA","USA","VNM","ZAF"],"kalemegdan":["SRB"],"kalten":["AFG","BGR","CAN","ESP","KGZ","MKD","POL","SRB","SYR","TJK","TKM","UKR","UZB"],"kanistern":["SRB"],"kapacitet":["BGD","DZA","GEO","IDN","IND","LKA","MAR","MDV","MMR","NGA","NPL","PAK","RWA","SRB","TUR"],"karton":["ARE","SRB"],"katastrofe":["BGD","DZA","GEO","IDN","IND","JPN","LKA","MAR","MDV","MMR","NGA","NPL","PAK","RWA","SRB"],"kennung":["ITA","SRB","USA"],"kennzeichen":["ALB","AUT","BEL","BGR","BIH","FRA","GNB","GRC","HUN","JAM","KEN","LKA","LVA","MDA","MEX","MKD","POL","PRT","PRY","ROU","RUS","SRB","SVN","TTO","TZA","URY"],"kennzeichnung":["CHL","HND","HRV","JPN","POL","SRB"],"kket":["AUS","BGD","BIH","BRA","CAN","CHL","CHN","COL","DZA","EGY","ETH","GBR","GEO","GHA","IDN","IND","ISR","JOR","JPN","KEN","KHM","KOR","LBN","LKA","MAR","MDV","MEX","MMR","MYS","NGA","NPL","PAK","PER","PHL","RUS","RWA","SAU","SEN","SGP","SRB","THA","TUN","TUR","UGA","UKR","USA","VNM","ZAF"],"klassischen":["BEN","BFA","FIN","GIN","IRL","ISL","KOR","MNG","NGA","POL","ROU","SRB","SVK","SVN"],"kleine":["CHN","COM","ERI","GHA","IND","ITA","KGZ","MLT","NOR","NRU","OMN","PER","SAU","SRB","TZA","USA","ZAF","ZMB"],"kleineren":["ARG","AZE","BIH","CHL","COD","CZE","ECU","EGY","GTM","HTI","JAM","JPN","KEN","KGZ","KHM","LBN","MAR","MDV","MOZ","NIC","PAN","SLV","SRB","SWE","TKM","TUR","VUT","ZWE"],"klimatischen":["ALB","BIH","BWA","CHL","CZE","DZA","ECU","FRA","HRV","ISR","ITA","LBY","MKD","MNE","NAM","NZL","PRY","PSE","SRB","SVK","SWE","SYR","TUR","UKR","ZWE"],"kliniken":["BOL","EGY","FJI","GEO","IDN","IND","KAZ","LBR","LBY","MLT","MNG","RUS","SRB","TUR","VNM","ZWE"],"kombinierte":["SRB"],"konstantinou":["ALB","GRC","SRB"],"konsularvertretungen":["SRB"],"kontaktaufnahmen":["MEX","SRB"],"kontaktiert":["ARE","ARG","ATG","BDI","BLZ","BRB","COD","COG","CPV","CZE","DJI","DMA","ECU","ESP","GRD","GTM","GUY","HKG","IRQ","KNA","LCA","LSO","MDA","MEX","MNG","MYS","NOR","RUS","SAU","SRB","SUR","SYC","TZA","USA","VCT"],"kontinental":["ALB","BLR","CHN","EST","FRA","IRN","KGZ","MDA","MKD","MNE","MNG","RUS","SRB","TJK","TUR","UKR","UZB","XKX"],"korper":["ALB","ARE","ARG","AZE","BEN","BFA","BGR","BIH","BLR","BOL","BRA","CHL","COD","COL","CUB","ECU","FIN","GHA","GIN","GUY","IND","IRN","KEN","MKD","MLI","MRT","NAM","NGA","OMN","PER","POL","PRT","PRY","ROU","RUS","SEN","SRB","SSD","SVK","SWE","TCD","UGA","UKR","USA","VEN"],"kosancicev":["SRB"],"kosovare":["SRB","XKX"],"kosovarische":["SRB","XKX"],"kosovarischen":["SRB","XKX"],"kosove":["SRB"],"kosovo":["ALB","MKD","MNE","SRB","XKX"],"kostenlose":["AZE","BEL","CHL","CRI","ITA","JAM","JPN","LAO","OMN","PER","SRB","THA","USA","VNM"],"kraljevo":["SRB","XKX"],"krig":["BIH","PHL","SRB","VNM"],"kunstlerischem":["SRB"],"kalikasthan":["NPL"],"kalte":["AFG","AND","ARM","AUT","BTN","CAN","CHL","EST","FIN","HRV","IND","IRN","ISR","KAZ","KGZ","LTU","LVA","MNG","NPL","PAK","PSE","RUS","SVN","SWE","USA","UZB","VUT"],"kanchenjunga":["NPL"],"kaotisk":["BEL","BGD","BGR","BRA","CHL","COL","DZA","EGY","ESP","ETH","FRA","GHA","HUN","IDN","IND","ISR","ITA","KEN","KHM","LBN","LKA","MMR","MYS","NGA","NPL","PAK","PER","POL","SAU","THA","TUN","TUR","UGA","UKR","VNM"],"kapurdhara":["NPL"],"karnataka":["BTN","IND","NPL"],"kashmir":["BTN","IND","NPL","PAK"],"kaski":["NPL"],"kasthamandap":["NPL"],"katastrophenschutz":["COL","CRI","GRC","NPL","PER","TUR"],"kathmandu":["NPL"],"katmandou":["NPL"],"katmandu":["BTN","NPL"],"kenntnisse":["BRA","GEO","IDN","NPL","RUS"],"kerala":["BTN","IND","NPL"],"khusibu":["NPL"],"kill":["BGD","BRA","BWA","CMR","CRI","ECU","FJI","HTI","IDN","IND","IRN","JOR","KEN","KHM","LAO","LBY","MAR","MEX","MLI","MNG","MWI","MYS","NAM","NGA","NPL","PER","PHL","PNG","RUS","RWA","THA","TUR","UGA","UKR","VNM","ZAF","ZMB","ZWE"],"kits":["ARE","KAZ","NPL"],"klare":["LKA","NPL"],"kleinen":["AFG","BWA","CHE","CHL","COD","COM","ETH","IND","KAZ","KGZ","KWT","LKA","MKD","MNG","NPL","PAK","PAN","QAT","SGP","SVK","TLS","TUR","TWN","USA","VEN"],"kleiner":["AGO","ALB","BRN","BTN","CAF","CAN","CMR","COG","CUB","DOM","DZA","GAB","GMB","GNQ","GRC","HTI","IRQ","JAM","KWT","LAO","LBN","LBY","MEX","MOZ","MYS","NPL","PAK","PNG","SAU","SDN","SWZ","SYR","THA","TLS","TTO","TZA","YEM","ZAF","ZMB","ZWE"],"klinikker":["BIH","DZA","GHA","JPN","NPL","RWA","SEN","USA"],"knowingly":["NPL","USA"],"koln":["NPL"],"kommerzielle":["BHR","CMR","CUB","DOM","ERI","LTU","MAR","MLI","NOR","NPL","POL","USA"],"komplicerede":["GHA","MMR","NPL"],"kondition":["BIH","MNE","NPL"],"konfiszierung":["BFA","BLR","ERI","ITA","NPL","POL","RUS","SGP","TCD"],"konsequente":["CZE","NPL","PRY"],"konsequenzen":["AFG","CUB","HRV","IDN","IRN","KAZ","NPL","RUS","SAU","TUN","TUR","VNM"],"konservativen":["BRN","NPL","PAK","VNM"],"konvertierbar":["GMB","LBY","MRT","NPL","SYC"],"kooperativ":["BFA","ERI","GNQ","KGZ","MLI","NPL","TJK","TUR","UKR"],"kopfschmerzen":["AFG","CHL","CUB","IND","IRN","KAZ","KGZ","MDV","NPL","PAN"],"korperlichen":["HUN","NPL","UKR","VNM"],"kostenintensiv":["AUS","BRA","IRN","NPL","VNM"],"kostenubernahme":["CRI","EGY","IND","IRN","NPL","TUR"],"kritisch":["BTN","CHN","COL","CUB","IRN","KEN","MEX","MOZ","NPL","PAK","PRY","SAU","URY","UZB"],"kritische":["EGY","IRN","KHM","MMR","NPL","RUS","SAU","THA","VNM"],"kuhlkette":["AFG","NPL","OMN","PAK"],"kulturgutern":["COL","GEO","IRQ","KHM","NPL","OMN","PER","UKR"],"kupandol":["NPL"],"kupondol":["NPL"],"kurzfristige":["AFG","ALB","AUS","BFA","BGR","BHR","BLR","BOL","CHL","CHN","COD","ECU","EGY","EST","FJI","GNB","KOR","LVA","NAM","NIC","NPL","PAK","PRT","SSD","SUR","TZA","XKX","ZAF"],"kvalitet":["NPL"],"kvinder":["BGD","BGR","BRA","COL","DZA","EGY","GEO","IDN","IND","JOR","JPN","KHM","LBN","LKA","MAR","MEX","MYS","NPL","PAK","SAU","SEN","TUN"],"khalifa":["ABW","AIA","ARE","ASM","ATA","BOL","BQ-BO","BQ-SA","BQ-SE","BRN","COD","COG","CUW","CYM","CZE","ESP","FRO","FSM","GLP","GNB","GRL","GUF","GUY","HKG","IRN","JOR","KOR","LAO","MAC","MDA","MMR","MRT","MSR","MTQ","MWI","NCL","NIU","PCN","PRI","PSE","PYF","REU","SJM","SLV","SXM","SYR","TCA","TGO","TKL","TWN","TZA","VEN","VGB","VIR","WLF","XKX"],"kingdom":["ABW","AIA","BHR","BQ-BO","BQ-SA","BQ-SE","CIV","CUW","CYM","CYP","DNK","GBR","GLP","GRL","IRL","IRN","KNA","MLT","MSR","NER","SAU","SXM","SYC","TON","TZA","VGB"],"kitt":["AIA","ATG","BRB","DMA","GRD","KNA","LCA","MSR","SXM","VCT","VGB"],"kommuneqarfik":["GRL"],"krone":["CZE","DNK","FRO","GRL","ISL","NOR","SWE"],"kaution":["ATG","AZE","BGR","BHS","BRB","CYP","CZE","DMA","DOM","EGY","GRD","GUY","KNA","LCA","MLT","SUR","TTO","VCT"],"kick":["BRB","GRD","LCA","TTO","VCT"],"kunden":["BGR","GAB","LCA","NZL","POL","SWE","TUR","VCT"],"kurvenreich":["ATG","BRB","DMA","GRD","GUY","JAM","KNA","LCA","LSO","NZL","SUR","SYC","TTO","VCT"],"kusten":["AUS","BLZ","CAN","COM","CRI","DJI","DNK","ECU","FSM","GTM","GUY","HND","HTI","IND","JAM","KEN","KNA","LBN","LCA","MDG","MEX","MYS","NOR","OMN","SLV","SOM","SYC","TZA","VCT","VEN","YEM","ZAF"],"kustennahe":["ARE","GNB","GRD","GUY","KNA","LCA","PAK","PAN","SUR","TTO","VCT"],"kustenwache":["ALB","ATG","ERI","GRC","GRD","KNA","LCA","TTO","VCT"],"kaufbeleg":["HUN"],"keiner":["ARM","AUT","BEL","CYP","EST","FIN","FRA","GRC","HUN","IRN","ITA","LUX","LVA","MDA","SMR","SVK","TUN","XKX"],"kelebija":["HUN"],"kinderreisepasse":["ARE","HUN","IDN","PRT"],"klinisch":["ALB","AUT","BGR","CYP","CZE","ESP","EST","FRA","GRC","HRV","HUN","MKD","TTO","XKX"],"komitat":["HUN"],"konfrontiert":["CUB","HUN","IRN","KGZ","MDA","THA"],"kongo":["AGO","ARE","BDI","BEN","BFA","BHR","CAN","COD","COG","COL","EGY","GHA","GIN","GRC","HUN","IND","IRQ","KEN","MAR","MKD","MLI","MRT","MUS","NAM","NGA","RWA","SEN","SSD","TCD","TUR","TZA","UGA","USA","ZMB"],"konstant":["HUN","ITA"],"kontaktdaten":["ALB","BIH","CHN","GNB","HUN","ISR","JAM","MNE","NAM","PAK","POL","PSE","SYC","TCD","TZA","ZAF"],"kontinentalklima":["ARM","BGR","BIH","CAN","CZE","HUN","LSO","PAK","SWE","TKM"],"kontrollabschnitt":["HUN"],"kontrolle":["ARE","AUT","BEL","BGR","BOL","CAF","CHN","COD","COL","CUB","CYP","CZE","DJI","DNK","ERI","ESP","EST","FIN","FRA","GEO","GHA","GIN","GRC","HRV","HTI","HUN","IRL","IRN","IRQ","ISR","ITA","JAM","LBR","LTU","LUX","LVA","MCO","MDA","MEX","MLT","NOR","POL","PRT","PSE","ROU","RUS","SMR","SOM","SVK","SVN","SWE","TCD","UKR","URY","USA","YEM"],"kontrolliert":["ALB","ARE","BDI","BEN","BFA","BRA","CHN","COG","COL","DOM","ERI","GAB","HTI","HUN","IRN","ISR","ITA","JOR","JPN","KEN","MAR","MDA","NGA","NIC","OMN","PAN","PSE","RUS","SSD","SYR","TCD","UKR","XKX","ZMB"],"korperbedeckende":["COM","DOM","FRA","GTM","HND","HTI","HUN","IDN","IRQ","ITA","KHM","LAO","MDV","MEX","MLT","MYS","NIC","PAN","SDN","SYR","TZA","YEM"],"korperstellen":["COM","CYP","DOM","FRA","GTM","HND","HTI","HUN","IDN","IRQ","KHM","LAO","MDV","MEX","MLT","MYS","NIC","PAN","SDN","SYR","TZA","XKX","YEM"],"korut":["HUN"],"kozpont":["HUN"],"kraftfahrzeug":["CYP","ETH","FRA","GEO","HUN","IRN","TUR"],"krankenversichert":["HUN"],"kreditkartenformat":["HUN"],"krim":["ARE","BEN","BFA","COD","GHA","GIN","GRC","HUN","IND","IRQ","KEN","MAR","MKD","MLI","MRT","NAM","NGA","RUS","SEN","SSD","TCD","TUR","UGA","UKR"],"kriminalitatsopfer":["HUN"],"kroatien":["HRV","HUN"],"kurzzeitkennzeichen":["HUN"],"kartenausstellenden":["PRT"],"kartenzahlung":["ALB","DJI","LBR","PRT"],"katastrofer":["CAN","ESP","FRA","HRV","PRT","USA"],"klein":["ALB","BWA","PRT"],"kning":["AUS","CAN","ESP","FRA","GEO","GHA","HRV","JPN","PRT","USA"],"konsularischen":["ARG","BLR","COG","COM","CPV","CYP","ERI","ESP","ETH","GBR","GEO","GRC","ITA","KGZ","LBY","LSO","MAR","PAN","PNG","PRT","RUS","SWZ","TLS"],"kreisverkehr":["AND","FRA","GBR","GRC","ITA","PRT","RUS"],"kreisverkehren":["AND","GRC","PRT"],"kaliningrad":["LTU","LVA","POL","RUS"],"kaliningrader":["POL"],"kamera":["BDI","BEL","BWA","CHN","COL","CUB","DNK","ECU","ETH","FJI","FRA","GNB","GNQ","GRC","GTM","IRN","JOR","LKA","MNE","POL","PRK","RWA","SAU","SLV","TCD","THA","ZMB"],"kantor":["POL"],"karteninhaber":["POL"],"katowice":["POL"],"kattowitz":["POL"],"killing":["ARM","BLR","COD","COL","ECU","ESP","IDN","KEN","LBN","MAR","MEX","NGA","PAK","POL","PRK","RUS","SWE","UGA"],"kilometer":["ASM","CAN","CHN","COK","ERI","FJI","HKG","ISR","JPN","KIR","KOR","LAO","LBN","MHL","MNG","NCL","NIU","NRU","PLW","PNG","POL","PRK","PSE","PYF","RUS","SLB","TKL","TON","TUV","VUT","WLF","WSM"],"kilometre":["BGR","CUB","DNK","EGY","ESP","ISL","ISR","KHM","LBR","LUX","MNE","MUS","NGA","PAK","PHL","POL","RWA","TCD","THA","TUR","USA"],"kilometro":["AGO","AUT","AZE","BRA","CHL","CMR","COM","ECU","ETH","FIN","KGZ","LSO","MEX","MRT","NAM","NZL","PAN","PER","PLW","POL","TCD"],"klinik":["CRI","DOM","HND","IRN","NIC","PAK","POL","QAT"],"kohleverbrennung":["POL"],"konin":["POL"],"koroszyn":["POL"],"kraftfahrtbundesamt":["POL"],"kraftwerken":["POL"],"krajowego":["POL"],"krakau":["POL"],"krakow":["POL"],"kramarska":["POL"],"kreditkartenbetrug":["AUS","BRA","CHL","EST","FJI","GHA","IDN","LKA","LTU","LVA","NAM","PAK","PHL","POL","SWZ","TWN","VNM","ZMB"],"kriegsbedingt":["POL","SOM"],"kukuryki":["POL"],"kunstgegenstande":["AUS","AZE","CHN","POL"],"kupno":["POL"],"kurs":["BIH","CZE","ERI","GAB","KGZ","LBN","MMR","POL","URY","VCT","VEN"],"kurzzeitige":["CAN","POL"],"kuznica":["BLR","POL"],"kassenschalter":["SVK"],"kinde":["AGO","ARE","BRA","BWA","CMR","CZE","GEO","HND","JOR","MDA","MOZ","NAM","SVK","UZB"],"kindergarten":["BGR","CHN","SVK"],"kindesentziehung":["DZA","MNG","SVK"],"kommune":["FRA","SVK","SWE"],"kontinentale":["AFG","HRV","LSO","LTU","NOR","ROU","SVK","SVN","SYR","TKM"],"konto":["BRA","COL","GBR","QAT","RUS","SVK"],"korona":["LTU","SVK"],"kosice":["SVK"],"kostenlo":["AUS","BGR","CHL","COK","COL","GMB","LAO","MAC","OMN","PNG","RUS","SVK","TWN","UKR"],"kramare":["SVK"],"kurorten":["SVK"],"karasovici":["HRV"],"karlovac":["HRV"],"keinesfall":["AFG","BHS","CIV","COG","CRI","ECU","EGY","ETH","HRV","IRN","IRQ","JAM","KEN","KGZ","MAR","MEX","MLI","MNE","MWI","NIC","PER","SDN","SSD","TJK"],"klaiceva":["HRV"],"klicken":["GTM","HRV"],"klinge":["GBR","HRV","SVN","TTO"],"kontrollverfahren":["HRV","LVA"],"kosovoconsular":["HRV"],"krankenhausbehandlung":["CZE","HRV","RWA","SWZ","ZAF"],"krankenkassen":["CZE","DNK","DOM","GBR","HRV","TUR"],"kredit":["ARE","AZE","BGD","BOL","BRA","BRN","BWA","CZE","DNK","DOM","DZA","FIN","GMB","GTM","GUY","HRV","IRL","ISR","JAM","JOR","KGZ","MNG","MRT","MWI","MYS","PSE","QAT","RWA","SEN","SLV","SWE","SYC","THA","UGA","URY"],"kroatisch":["BIH","HRV"],"kroatische":["BIH","HRV"],"kroatischem":["HRV"],"kroatischen":["HRV"],"kroatisk":["HRV"],"kroatiske":["HRV"],"kuna":["HRV","PAN"],"kuste":["AGO","AUS","BIH","BRN","CIV","CMR","CRI","DJI","DZA","ECU","EGY","ERI","ESP","GAB","HRV","ISR","KEN","KHM","LBN","LBY","MMR","MNE","MUS","MYS","NAM","NGA","NIU","PER","PSE","SLV","STP","SWE"],"kustenorten":["EGY","HRV"],"kysten":["CHL","DZA","HRV","KEN","PER","TUR","ZAF"],"kapitelj":["BIH","SVN"],"kaufbestatigung":["SVN"],"kaufen":["ARG","BRA","CUB","CZE","DOM","ERI","FJI","LAO","MLT","PAK","PAN","PRY","RUS","SVN","THA","TUR","TWN"],"klettern":["SVN"],"klinicni":["SVN"],"komenskega":["SVN"],"kommunizieren":["SVN"],"konfisziert":["ARE","AZE","CHN","CYP","LAO","MRT","NIC","SAU","SVN","THA","TUN","UGA"],"kongresni":["SVN"],"konzentriert":["CHN","LBN","SVN"],"krafte":["AUT","IDN","MMR","SOM","SVN","SYR","TGO"],"kraftfahrzeuge":["ARE","DOM","FRA","NOR","QAT","RUS","SVN","UKR"],"karlsbad":["CZE"],"kiosk":["BGR","CRI","CZE","EGY","FRA","GMB","ITA","KAZ","KGZ","LAO","LVA","MEX","MMR","RUS","TUR","USA"],"klasse":["BGD","CZE","MEX","MKD","VNM","ZAF"],"kleinere":["AGO","ALB","BRA","CHL","COD","CRI","CZE","ETH","GBR","GNB","ISL","JAM","KAZ","KHM","LBR","LIE","LKA","MNE","NIC","ROU","SLE","SLV","SWE","URY","VUT","ZMB"],"kleinkinder":["CHN","CZE","MYS","SGP"],"kombination":["CZE","NZL","THA"],"kontrollieren":["BFA","BOL","BRA","COL","CPV","CUB","CYP","CZE","DOM","GMB","GNQ","GRC","KAZ","LBY","MLI","MMR","NAM","PAN","PER","SUR","TZA","VEN","VNM","ZMB"],"kopie":["AGO","AZE","BRA","BWA","CAN","CHL","CHN","CMR","CZE","ECU","GHA","GNQ","GRC","IRN","IRQ","JOR","MAR","MDA","MEX","MWI","NAM","NIU","TGO","TUN","USA","VNM","ZAF"],"koruna":["CZE"],"kostenrahmen":["CZE"],"kraftstoff":["BOL","CZE","ETH","KGZ","MOZ","RUS","TCD","ZMB","ZWE"],"kraftstoffen":["CZE","MOZ","MWI","NGA","SLE","ZWE"],"krankenversicherte":["CZE","TUR"],"kampf":["BEN","MWI","PER","SAU"],"karawanen":["MWI"],"karonga":["MWI"],"kasungu":["MWI"],"katastrophenhelfer":["BEN","BFA","GIN","MWI","NGA","UGA"],"kayaking":["ARM","ATG","DOM","ECU","GHA","JAM","KHM","LAO","MHL","MWI","PER","RWA","THA","TON","UGA","VNM"],"kenyatta":["KEN","MWI"],"kidnap":["AFG","AGO","ARG","BEN","BFA","BLR","BOL","BRA","CHL","CIV","CMR","COD","COL","DZA","ECU","ETH","GHA","GIN","GMB","GTM","HTI","IRQ","ISR","KEN","LBN","LBY","MDG","MEX","MLI","MMR","MOZ","MWI","MYS","NER","NGA","NIC","PAK","PSE","SDN","SEN","SOM","SSD","SYR","TCD","TGO","TUN","TZA","UGA","YEM","ZAF"],"kidnapped":["AFG","ARG","BEN","BFA","BLR","BRA","CAF","CHL","CMR","COL","DZA","ECU","EGY","ERI","ETH","GHA","GIN","GMB","GTM","HTI","IDN","IRQ","ISR","KEN","LBN","LBY","MEX","MLI","MMR","MOZ","MRT","MWI","MYS","NER","NGA","PAK","PER","PHL","PNG","PRY","PSE","SDN","SEN","SOM","SSD","SYR","TCD","TGO","THA","TUN","TZA","UGA","VEN","YEM","ZAF"],"kmph":["MWI","WSM"],"krank":["ARM","AZE","BDI","BEN","BFA","CIV","COD","CPV","DJI","ERI","ETH","GHA","GIN","GMB","GNB","IND","KEN","LBR","MDG","MLI","MRT","MWI","NAM","NER","NGA","QAT","RWA","SEN","SLE","SOM","SSD","TCD","TGO","UGA","UKR"],"kuhe":["FJI","IRQ","MWI"],"kurze":["ALB","ARE","AUT","BRN","ISR","LAO","LKA","MNG","MWI","PSE","SLV","SSD","USA"],"kwacha":["MWI","ZMB"],"kennen":["AUS","GBR","GHA","GRD","GTM","HND","HTI","JAM","KHM"],"kingston":["ATG","BHS","CYM","GBR","JAM","KNA","TCA"],"kurzerem":["ATG","ZAF"],"kamerun":["CAF","CMR","GAB","GNQ","STP","TCD"],"kasernen":["BFA","COG","GAB","GIN","LBN","MLI","PAK","SOM","SYR","YEM"],"klade":["CIV","GAB","TCD"],"kleinbusse":["AGO","BGR","BHS","BWA","DJI","GAB","GHA","GNB","GTM","KEN","MLI","PAK","TLS","TTO"],"kontinent":["CIV","GAB","TCD"],"korperflussigkeiten":["AUS","BDI","CIV","COD","GAB","GNQ","ISR","PSE","RWA","SSD","TCD","UGA","ZAF"],"krankheit":["AFG","AGO","ARG","ARM","BEL","BGD","BOL","BRA","CAF","CHN","CMR","COG","COL","COM","ECU","EGY","GAB","GEO","GNQ","GUY","KAZ","KHM","MNG","MOZ","PER","PRY","SAU","SDN","SGP","STP","SUR","SYR","TJK","TKM","TUV","TZA","VEN","YEM","ZMB"],"krankheitsgefuhl":["CHL","GAB","GNQ","IDN"],"kustenorte":["CMR","GAB","NGA","STP"],"kabanbay":["KAZ","KGZ","TJK","TKM","UZB"],"kamelen":["IRQ","JOR","KAZ","KGZ","KWT","MDG","OMN","SAU","SDN","YEM"],"karaganda":["KAZ"],"karasai":["KAZ"],"karmakchi":["KAZ"],"kasachische":["KAZ"],"kasachischem":["KAZ"],"kasachischen":["KAZ"],"kasachischer":["KAZ"],"kasachstan":["AZE","BLR","KAZ","KGZ","TKM"],"kazaja":["KAZ","KGZ"],"kazajistan":["KAZ"],"kazajo":["KAZ"],"kazajstan":["AZE","KAZ","KGZ"],"kazakh":["KAZ","KGZ"],"kazakhstan":["AZE","IRN","KAZ","KGZ","TJK","TKM","UZB"],"kazakhstani":["KAZ"],"kazalinsk":["KAZ"],"kazybek":["KAZ","TJK"],"kirgisistan":["BLR","KAZ","KGZ","TJK","UZB"],"kirguistan":["KAZ","KGZ","TJK","UZB"],"kokshetau":["KAZ"],"kommunikationsmittel":["ARE","BFA","BHR","CAF","COD","COL","ECU","ETH","IRN","IRQ","ISR","JOR","KAZ","KEN","KWT","LBN","LBY","MLI","MRT","NER","OMN","PAK","PSE","QAT","RUS","SAU","SDN","SSD","SYR","TUR","YEM"],"konfession":["KAZ"],"kosmonavtov":["KAZ","KGZ","TJK"],"kranke":["FRA","GBR","IRN","KAZ","KGZ","KHM","MNG","VEN"],"krankheiten":["AGO","AZE","BGR","BIH","BLR","CMR","DOM","JOR","KAZ","KOR","LAO","MKD","MNG","NIC","RUS","RWA","SAU","THA","UKR","XKX"],"kyrgyzstan":["KAZ","KGZ","TJK","UZB"],"kyzylorda":["KAZ"],"karibikkuste":["CRI","HND"],"kenia":["BDI","COM","EGY","ETH","HND","KEN","RWA","SOM","SSD","SYC","TZA","UGA"],"kielsa":["HND","NIC"],"kilo":["ETH","HND","TUR"],"kleinstmengen":["ALB","ARE","ARG","EST","HND","LVA"],"klimatisiert":["GHA","HND"],"kontaminierte":["GTM","HND","HTI","IND","JAM","MEX","NIC","PAN"],"korrekt":["BRA","COL","CRI","FRA","GTM","HND","LKA","MEX","NIC","PAK","PAN","PER","SLV"],"kurzaufenthalt":["ARE","BGD","HND","LSO","PLW","RUS"],"kutane":["BLZ","CRI","GTM","HND","MEX","PAN"],"kala":["AFG","BGD","BRA","CHN","CMR","DJI","DZA","ERI","ESP","ETH","GEO","GRC","IND","IRN","ITA","KEN","MAR","PRY","SDN","SOM","SSD","SYR","TCD","UGA","YEM"],"kamerunische":["CMR"],"kaufpreise":["CMR"],"keen":["AUT","BEN","BRA","CHE","CMR","DOM","EST","ETH","FRA","GEO","JAM","KEN","KHM","LBN","LKA","LTU","LVA","MEX","NGA","QAT","SEN","UKR","ZAF","ZMB"],"kennedy":["BFA","BRA","CMR","NER"],"kissing":["ARE","ARM","BRB","CMR","COM","DJI","DZA","ERI","KNA","LAO","MDG","MUS","NER","OMN","QAT","SEN","SOM","TZA","ZMB"],"kontaktieren":["CHN","CMR","COL","CPV","CRI","CUB","GBR","IND","KGZ","KHM","KWT","LAO","LBN","LKA","MAR","MEX","MLI","MUS","PER","SLV","SOM","SWZ","USA","UZB","VEN"],"kraterseen":["CMR"],"kriminell":["CMR","KEN","NGA","PAK","SOM"],"kumba":["CMR"],"kumbo":["CMR"],"kunstwerke":["CMR"],"kurzer":["ARE","ARM","BGD","CMR","GEO","LTU","MDV","PAN","PER","SAU","SDN","SLV","THA","TLS","UKR","YEM"],"kurzfristiger":["CMR"],"kustenregionen":["CHL","CHN","CMR","KEN","MMR","SYR","TLS","TZA","VNM"],"kalenderjahr":["ARM","BLR","BOL","BWA","ECU","NOR","THA"],"kalendertag":["BLR"],"kalendertage":["BLR","KOR"],"kalendertagen":["BLR","LKA"],"kamenny":["BLR","LTU"],"kamienny":["BLR"],"khmelnitskogo":["BLR"],"kinderlosigkeit":["BLR"],"kinderreisepassen":["BLR","GBR"],"kizhevatova":["BLR"],"kleinsten":["BLR","ECU","GHA","IDN","SLV"],"kleinster":["BLR","CYP","IND","ITA","MAR","MLT","TUN"],"konnte":["ALB","BLR","BRA","CUB","DZA","ERI","GEO","ISL","KHM","LAO","LKA","MEX","MLI","MMR","MRT","PHL","THA","USA","YEM"],"konstruierter":["BLR","IRN","RUS"],"konsumguter":["BLR"],"kontrollma":["BLR"],"korrespondenz":["BLR","RUS"],"kostenpflichtige":["ARE","BLR","CUB","ESP","FRA","GEO","KHM","KNA","MEX","RUS","TJK"],"kraft":["BLR","BWA","CHN","GNB","IDN","IRL","IRN","IRQ","JPN","KHM","KWT","MMR","SEN","SLE","SLV","USA"],"krankenschwestern":["AZE","BLR","UKR"],"krasnaja":["BLR","RUS"],"kropotkinsky":["BLR"],"kruglowka":["BLR","RUS"],"kyrillischen":["BLR"],"karpaten":["ROU"],"keller":["ROU"],"kenntlich":["LKA","ROU","UZB"],"klarung":["ARM","AZE","EGY","GEO","KGZ","MNE","NIC","OMN","ROU","TUR","WSM","ZMB"],"kopieren":["BGR","FJI","MEX","ROU","SLV"],"krei":["AND","ITA","ROU"],"kreditinstitut":["GUY","RWA","TZA"],"kriterien":["BWA","CAN","CRI","GHA","GUY","IND","ISR","ITA","LBR","MDG","NAM","PSE","RWA","SSD","SWE","VUT"],"kustengebieten":["AUS","GUY","IND","SYR"],"kensington":["KNA","TKM","VCT"],"kingstown":["VCT"],"karl":["AUT","BLZ","KIR","MOZ","NOR","NRU"],"kassen":["AUT","BGR","ESP","GTM","MAR","SAU","THA","TUN"],"kassenarzt":["AUT"],"kaufdatum":["AUT"],"kaufnachwei":["AUT"],"khevenhuller":["AUT"],"kirchenfeldstrasse":["AUT","CHE","DZA","LIE"],"klebevignette":["AUT"],"klebevignetten":["AUT"],"klotz":["AUT"],"konsumentenschutz":["AUT"],"kontinentalem":["AUT"],"korp":["AUT"],"kraftfahrzeugregister":["AUT"],"kadaver":["BWA","ERI","KEN","LSO","NAM","RWA","SSD","UGA"],"kampala":["RWA","SSD","UGA"],"katastrophalen":["NGA","SSD"],"kazanche":["DJI","ETH","SSD"],"kenya":["BDI","COM","ERI","ETH","IND","KEN","RWA","SDN","SOM","SSD","UGA"],"kenyan":["KEN","MDG","SDN","SSD"],"kenyapostal":["KEN","SOM","SSD","UGA"],"kenyatelephone":["KEN","SOM","SSD","UGA"],"ketema":["DJI","ERI","ETH","SDN","SSD"],"kifle":["DJI","ERI","ETH","SDN","SSD"],"klimaangepasste":["SSD"],"konflikte":["AFG","COG","EGY","GHA","GIN","GTM","IND","ISR","KEN","LBY","LKA","MMR","NGA","PSE","SSD","TCD","YEM"],"konflikten":["COD","DZA","IRN","LBN","NGA","RWA","SSD","TUR"],"konsularangelegenheiten":["BDI","LBR","SSD"],"kontaktpersonen":["BDI","RWA","SSD","TLS","TZA"],"kontinuierlich":["BGD","COL","JPN","PAK","SSD"],"kriegerischer":["MMR","SDN","SSD"],"kurzen":["MOZ","NAM","NZL","SLV","SSD"],"kurzfristigen":["AFG","AZE","BIH","BRA","CUB","EGY","GNQ","JOR","LBN","MDG","MMR","MNG","NGA","PAK","PRK","SSD","SYR","TGO","TZA","UKR","ZWE"],"katastrophenvorsorge":["JAM"],"king":["AUS","BHR","BHS","BLZ","BTN","CYM","EGY","GBR","ISR","JAM","JOR","KHM","MAR","PNG","PSE","RWA","SAU","SWZ","TCA","THA","ZAF"],"knutsford":["JAM"],"konzerte":["JAM"],"kreditkartenmissbrauch":["CIV","JAM","MEX","MKD","SYC"],"kreditkartenzahlung":["CRI","ECU","JAM","JOR","MEX","PAN","TTO"],"kreuzfahrtschiffen":["BRA","ESP","GBR","JAM","KNA","OMN","RUS"],"kachin":["MMR"],"kalmaegi":["IDN","KHM","LAO","MMR","MYS","PHL","SGP","THA","TLS","VNM"],"karten":["AUS","BLZ","BRA","CUB","ERI","FJI","GNQ","IDN","IRN","JPN","KHM","LAO","LBN","LBY","MMR","PAN","PHL","RUS","TWN","VNM","ZAF"],"kaufquittung":["GIN","MMR"],"kaum":["AGO","AZE","BDI","BHR","BOL","BRN","CAF","DJI","DZA","FSM","GHA","GMB","GNB","GNQ","HKG","IDN","KOR","KWT","LAO","LSO","MAR","MMR","NRU","PAN","PNG","SAU","SEN","TCD","TLS","TZA","VEN","XKX"],"kayah":["MMR"],"kayin":["MMR"],"kinderlahmung":["AFG","BRN","IRN","IRQ","JOR","MDV","MMR","PAK","SAU","SDN","TLS","YEM"],"klassische":["CHN","HKG","IDN","KHM","MMR","MYS","VNM","XKX"],"konflikter":["MMR"],"konnten":["AGO","BFA","CHN","CIV","CPV","CUB","EGY","ETH","GEO","GRC","HTI","IRN","ISR","KHM","LAO","LBN","LKA","LSO","MMR","NZL","PRK","PSE","RUS","SGP","SLV","SOM","TJK","TUR","TZA","UKR","VEN","ZAF"],"kontanter":["CHN","LBN","MMR","NGA","RUS"],"kontrol":["CHN","ETH","GEO","JOR","JPN","MMR","PAK","RUS","SAU","TUN","UKR","USA"],"kreditkort":["JPN","LBN","MEX","MMR","PAK","PER","PHL","RUS","ZAF"],"kriegerischen":["BDI","MMR","UKR"],"kriegsrecht":["COD","MMR","RUS"],"kritik":["ARE","BRN","ERI","MMR","RUS","THA"],"kultur":["CHN","IRQ","JPN","KHM","LBY","MMR","SAU","SOM","SYR","TUR","UKR","YEM"],"kunftig":["AUS","BGD","CHN","HKG","IDN","IND","IRQ","JPN","KOR","MDV","MMR","MOZ","MYS","NZL","PHL","SGP","SYC","THA","VNM"],"kyangin":["MMR"],"kyar":["MMR"],"kyat":["MMR"],"kapalai":["MYS"],"karakit":["MYS"],"kauflich":["EGY","MYS"],"kedah":["MYS"],"kelantan":["MYS"],"kidnapning":["BGD","COL","EGY","GEO","GHA","IDN","IND","KEN","LBN","MYS","PAK","PHL","SEN"],"kidnapninger":["COL","DZA","ETH","GHA","JPN","MEX","MYS","NGA","PAK","PER","PHL","TUN"],"kinabalu":["MYS"],"kinabatanga":["MYS"],"kinabatangan":["MYS"],"klcc":["MYS"],"klia":["MYS"],"knee":["AFG","ARE","BHR","COM","EGY","ETH","FJI","GMB","GRC","IRN","ISR","KEN","KHM","KWT","LAO","MDV","MYS","OMN","PSE","QAT","SAU","SLB","VNM","YEM"],"konsultieren":["LKA","MYS","SGP"],"kontrollere":["MYS"],"korperliche":["AUS","COL","GRC","IRN","ITA","JOR","MYS","SGP","TTO","USA"],"kota":["MYS"],"kuala":["BGD","MUS","MYS"],"kualalumpur":["MYS"],"kuantan":["MYS"],"kudat":["MYS"],"kunak":["MYS"],"kurzaufenthalte":["BGD","COD","JPN","MYS","PAK","TWN"],"kustengewasser":["MYS","NGA","YEM"],"kustengewassern":["MYS","RUS","YEM"],"kystomradet":["EGY","KEN","MYS"],"kalt":["CHL","KOR","PRK"],"kontaktaufnahme":["AZE","BHR","BWA","CRI","DOM","MDA","NRU","PAK","PLW","PRK","SAU","TGO","TUR"],"kontrollpersonen":["PRK"],"kontrollpunkten":["ISR","MDA","PRK","PSE","TCD"],"korea":["CHN","HKG","JPN","KOR","MNG","PRK","USA"],"korean":["CHN","JPN","KOR","PRK"],"koreanische":["PRK"],"koreanischen":["KOR","PRK"],"koreanischer":["KOR","PRK"],"koreapostal":["KOR","PRK"],"koreatelephone":["KOR","PRK"],"koreax":["KOR","PRK"],"koryo":["PRK"],"kraftfahrzeugen":["AUS","BHR","BOL","CYP","ETH","FRA","ISL","PRK","SEN","UGA"],"kritisieren":["PRK"],"kaohsiung":["TWN"],"katastrophenfall":["TWN"],"keelung":["TWN"],"kinmen":["TWN"],"komfortabel":["TWN"],"kontakten":["ALB","JPN","MNG","NAM","NGA","TWN","USA","XKX"],"kamenge":["BDI"],"kampfhandlungen":["ARE","BDI","BHR","CAF","COD","COL","ERI","ETH","IRN","IRQ","ISR","JOR","KWT","LBN","LBY","MLI","OMN","PAK","PHL","PSE","QAT","SAU","SDN","SOM","TJK","TUR","UKR","YEM"],"kampfmittel":["BDI","KHM","MAR","THA"],"kanyosha":["BDI"],"kasai":["AGO","BDI"],"kayanza":["BDI"],"kenntni":["AFG","AZE","BDI","BOL","BRN","CHL","CHN","ECU","HKG","IDN","IRN","KHM","PAK","PER","SYR","THA","TLS","TUR"],"kibira":["BDI"],"kigali":["BDI","RWA","UGA"],"kinanira":["BDI"],"kinondoni":["BDI"],"kira":["BDI"],"kivu":["BDI","COD","RWA","UGA"],"knapp":["BDI","COM","GEO","ISR","LKA","MEX","PHL","PSE"],"knifepoint":["BDI","DOM","ETH","MRT","SLE"],"kobero":["BDI"],"kommunen":["BDI","GRC","ITA"],"konsularaufgaben":["BDI","FJI","GMB","LBR","STP","TCD"],"kontinuierliche":["BDI","BEN","BFA","CIV","GHA","GIN","GMB","GNB","LBR","MLI","MRT","NER","SEN","SLE","TGO"],"kaolack":["SEN"],"kaye":["MLI","MRT","SEN"],"kedougou":["SEN"],"kkeligt":["CAN","CHN","ISR","KEN","PAK","RWA","SAU","SEN","TUR","VNM"],"kleiden":["GMB","LKA","SEN"],"kolda":["SEN"],"kommentarer":["CAN","CHN","GEO","ISR","PAK","RWA","SAU","SEN","TUR","VNM"],"konko":["GMB","SEN"],"konomisk":["SEN"],"korite":["SEN"],"kustenregion":["CIV","FIN","FRA","GMB","KEN","LBR","MOZ","NAM","PAK","SEN","SWE","TZA"],"kakulaisland":["VUT"],"kava":["FJI","VUT"],"kevin":["FRA","VUT"],"knock":["VUT"],"kontaminiert":["AFG","BGD","CRI","TTO","UZB","VUT"],"korallenriffen":["VUT"],"koch":["AFG","KIR","LKA","NRU","OMN"],"krankenhausaufenthalt":["NRU"],"kameraausstattung":["NAM"],"kartenlesegerat":["NAM"],"kasse":["CRI","NAM"],"katima":["NAM","ZMB"],"katutura":["NAM"],"katwitwi":["NAM"],"kavango":["NAM","ZMB","ZWE"],"khoma":["NAM"],"klimaanlage":["NAM"],"kofferraum":["BIH","NAM","ZAF"],"kongola":["NAM"],"kunene":["NAM"],"kurzester":["ESP","LBN","NAM"],"kutako":["NAM"],"kaperungen":["KEN","MDG","OMN","SOM","SYC","TZA","YEM"],"kategorie":["AND","BGR","BHS","KHM","MDG","UGA","VNM","ZMB"],"kaufquittungen":["MDG"],"kilogramm":["MDG"],"kleidungsstucken":["COM","KWT","MDG","SDN","TZA"],"kopfbedeckungen":["COM","MDG","SDN","TZA"],"kriminalitatsbelastung":["MDG"],"kustenstadten":["MDG","TZA"],"keih":["ERI"],"keren":["ERI"],"kompetenten":["ERI","SAU","TUR"],"konkreten":["BGR","BOL","COL","ERI","EST","GEO","KEN","QAT","SLV"],"konsularischer":["ERI","GEO","LAO","NIC","SYR","UKR","VNM"],"konvertierbare":["ERI"],"kustenebene":["ERI","ISR","PSE","YEM"],"kailash":["IND"],"kalkutta":["BTN","IND"],"karve":["IND"],"kaschmir":["IND","PAK"],"kategorien":["ARG","CUB","IND","KHM","SGP","USA"],"kendra":["IND"],"keventer":["IND"],"khalistani":["IND"],"kiran":["IND"],"kokilaben":["IND"],"kolkata":["IND"],"kommercielle":["IND","JOR","KEN","LBN","PAK","SAU"],"kommunikation":["ARE","BTN","CHL","CUB","IND","IRN","JPN","KGZ","MRT","PAK","RUS"],"konferenzvisa":["IND"],"konfliktlinien":["IND"],"konkret":["IND"],"konservativt":["BGD","EGY","IDN","IND","ISR","PAK"],"kontaminierten":["AUS","CIV","IND","LBN","PAN","TCD","ZAF"],"korperkontakte":["IND"],"korrekte":["BRA","CHN","COL","DOM","ECU","ESP","IND","IRN","LKA","TJK"],"kulgam":["IND"],"kulturbewusste":["IND","TUR"],"kurla":["IND"],"kyster":["GBR","IND"],"kadiogo":["BEN","BFA"],"katze":["BFA","CIV","COL","MRT","SLE","TUN"],"kenedugu":["BFA"],"kizerbo":["BEN","BFA"],"koffer":["BFA","MNE","USA"],"konvoi":["AFG","AGO","BFA","CAF","COD","COG","DJI","GHA","GIN","KEN","LBR","MLI","MRT","NGA","QAT","SOM","YEM"],"kopienga":["BFA"],"kossi":["BFA"],"kourtiagou":["BEN","BFA"],"krimineller":["AFG","BFA","BOL","BRA","HTI","IRQ","MEX","NER","NGA","PAK","PAN","TGO"],"kulpelogo":["BFA"],"kulturveranstaltungen":["BFA"],"kuluba":["BFA"],"kartenmaterial":["SWE"],"klar":["ARE","CIV","KGZ","SAU","SWE","SYR","UKR"],"klarabergsgatan":["SWE"],"klarabergsviadukten":["SWE"],"kleinstbetrage":["DNK","FIN","SAU","SWE"],"kommunikationsgerate":["ETH","SWE"],"kontaktsperren":["SWE"],"krankheitsfall":["BGR","BWA","CHE","DNK","ESP","GTM","LTU","MAR","NZL","RUS","SAU","SWE","THA","TUN"],"kravet":["SWE"],"kriseinformation":["ISL","SWE"],"krisinformation":["SWE"],"krona":["ISL","SWE"],"kuhle":["SWE"],"kiribati":["ASM","COK","FJI","FRA","KIR","NIU","NZL","PYF","SLB","TKL","TON","WSM"],"kaboul":["AFG"],"kabul":["AFG","PAK"],"kanale":["AFG"],"kandahar":["AFG","PAK"],"keimen":["AFG","UZB"],"kenntnisstand":["AFG","COD","DJI","GIN","ISR","PSE","RUS","TCD"],"khorasan":["AFG","IRN","PAK","UZB"],"kompletten":["AFG","CRI","PAK"],"korperstrafen":["AFG","BRN","IRN","PAK","SAU"],"kriegshandlungen":["AFG","UKR"],"kriegswirren":["AFG","YEM"],"kassettenrecorder":["KIR"],"kieia":["KIR"],"kiribatipostal":["KIR"],"kiribatitelephone":["KIR"],"kiribatitourism":["KIR"],"kiritimati":["KIR"],"kone":["NCL"],"koumac":["NCL"],"koutio":["NCL"],"kuindo":["NCL"],"kaleveleve":["WLF"],"kayak":["ARG","AUS","BLZ","FJI","TON"],"kolofo":["TON"],"konigreich":["BTN","FRA","GBR","IRL","ISL","ISR","NOR","PSE","SAU","SWZ","TON"],"karen":["ISL"],"keflavik":["ISL"],"khat":["CHN","DJI","EGY","ETH","ISL","NOR","SOM","ZAF"],"kikjufjara":["ISL"],"kleinstadt":["ISL"],"kopavogur":["ISL"],"kroner":["ISL"],"kuhlen":["BWA","ISL","PAK"],"kanal":["BEL","BHS","PAN","PER","SLV"],"klick":["BEL"],"kunstlaan":["BEL"],"kvarter":["BEL"],"kauftag":["BGR"],"kiro":["ARM","BGR","GEO"],"knyaginya":["BGR"],"kompensationsgebuhr":["BGR"],"konsequenz":["BGR","NZL"],"kontrollierenden":["BGR","GRC","KEN","MEX","PRY"],"kulturministerium":["AZE","BGR","GEO","GRC","RUS","TUR"],"kurzzeitig":["BGR","LBN","PAK"],"kamele":["ARE","BHR","IRQ","JOR","KEN","KWT","OMN","QAT","SAU","SDN","YEM"],"kommerzieller":["BRA","HTI","YEM"],"konfliktgebieten":["YEM"],"kontrollierten":["MAR","MEX","UKR","YEM"],"kontrollposten":["GIN","LBY","PAN","SDN","SYR","YEM"],"krankheitspravention":["BIH","GMB","GNB","JOR","KWT","LBR","MKD","OMN","SAU","SDN","SLE","STP","YEM"],"kriminellen":["BGD","BOL","BRA","ECU","GHA","HTI","LAO","LKA","MAR","MEX","MLI","NGA","SLB","THA","YEM"],"ksaembassy":["BHR","OMN","SAU","YEM"],"kustenstra":["DJI","LBN","YEM"],"kampanien":["ITA"],"kartendiensten":["ITA"],"katastrophenschutze":["ESP","GRC","ITA","NZL"],"kiesel":["ITA"],"kofferraumabdeckung":["ITA"],"komplettem":["ITA"],"komplex":["ITA","KWT"],"komplizen":["ITA","MNG"],"konfiskation":["ITA","LBN"],"kopf":["ITA","MOZ","PAN","TZA"],"kreislauf":["GRC","ITA","KWT"],"kreuzungen":["BGD","CAN","CHL","ESP","FRA","GBR","GHA","ITA","LIE","PAK","UGA","USA","ZAF","ZWE"],"kufferter":["ITA"],"kaart":["EST"],"katzenaugen":["EST"],"keskhaigla":["EST"],"kinderprostitution":["EST","LSO","SWZ","ZAF"],"kliinikum":["EST"],"klliinikum":["EST"],"kohtla":["EST"],"koidula":["EST","RUS"],"kooli":["EST"],"kosmo":["EST"],"kullasepa":["EST"],"kaliningrado":["LTU"],"karakter":["BGD","DZA","IDN","JPN","KHM","LTU","PAK","SAU","TUN","VNM"],"kasa":["COD","LTU"],"kauna":["LTU"],"klaipeda":["LTU"],"knmm":["LTU"],"konzept":["IRN","LTU"],"kotlovka":["LTU"],"krankheitsfallen":["LTU","VNM"],"kurische":["LTU","RUS"],"kurischen":["LTU"],"kalcheggweg":["CHE","LIE"],"kantonal":["CHE"],"kantone":["CHE"],"kantonspital":["CHE"],"kantonsspital":["CHE"],"kinderspitalzurich":["CHE"],"kirchenfeldstr":["CHE"],"klebe":["CHE"],"klingel":["CHE"],"komplett":["CHE","KEN","UZB"],"kontrollschild":["CHE","LIE"],"kostenruckerstattung":["CHE"],"krankenversicherungen":["ARE","CHE"],"kreuzstrasse":["CHE"],"kraftig":["AUS","BIH","FRA","GBR","IRL","ISR","MAR","MDV","UGA"],"kurzem":["IRL","KHM","VNM"],"kastrup":["DNK"],"kleidungsstuck":["DNK"],"kommerziellen":["CHN","COD","CUB","DJI","DNK","GIN","MOZ","NOR","SOM","TUR","VEN"],"kongen":["DNK"],"kopenhagen":["DNK"],"koranverbrennungen":["DNK"],"kreuzfahrten":["CUB","DNK","GBR"],"kristianiagade":["DNK"],"kritischer":["ARE","ARG","DNK","KWT","QAT","THA"],"karthala":["COM"],"kleider":["COM","THA"],"komoren":["COM"],"komorische":["COM"],"komorischen":["COM"],"konsumieren":["CIV","COM","MLT","OMN","USA"],"korperschaden":["COM","SDN","TZA"],"kostet":["AUS","BHR","COM","CUB","NIC","SGP","UGA"],"kwassa":["COM"],"kappe":["MOZ"],"kaunda":["AGO","MOZ","SWZ","ZMB"],"kenneth":["AGO","MOZ","SWZ","ZMB"],"korruptionsbekampfung":["MOZ"],"korruptionsfalle":["MOZ"],"kustenbereich":["MOZ","UKR"],"kairaba":["GMB"],"keinem":["GMB","MAR","PHL","SWZ"],"keinster":["GMB"],"kindesmissbrauch":["CRI","GMB","KEN","PHL","USA"],"knowing":["CHL","GMB"],"kontrollstellen":["GMB","LBN","UKR"],"kaivopuisto":["FIN"],"kalliolinnantie":["FIN"],"kati":["FIN","MLI"],"kela":["FIN"],"klimatische":["FIN"],"kraftverkehr":["FIN"],"kustavi":["FIN"],"kairo":["EGY","ISR","PSE"],"kanfe":["ISR"],"karkur":["ISR","PSE"],"kerem":["ISR"],"kfar":["ISR","LBN"],"kippur":["ISR","PSE"],"kiryat":["ISR"],"klimazonen":["ISR","PSE","USA"],"krankenwagen":["FJI","ISR","PSE"],"kriegszustand":["ISR","PSE"],"kurzzeitaufenthalte":["ISR","KOR","PSE"],"kurzzeitigen":["ISR","MEX","PAK","PSE"],"kustenabschnitten":["ISR","PSE","SYC"],"kanaldeckel":["SLV"],"kooperative":["SLV"],"kreditkartendaten":["SLV"],"kryptowahrung":["SLV"],"kundige":["KGZ","SLV"],"kaedi":["MRT"],"kankossa":["MRT"],"kaufer":["AUS","GEO","MRT"],"kaufvertrag":["MRT"],"keur":["MRT"],"khabou":["MRT"],"khayma":["MRT"],"kiffa":["MRT"],"kissi":["MRT"],"konate":["MRT"],"kontaktmoglichkeiten":["GEO","MRT"],"kulturellen":["ARE","CHN","GHA","MRT","PNG","QAT"],"kundgebungen":["BIH","GTM","IRN","IRQ","LBN","LKA","MLI","MRT","NGA","RUS","SYR","THA","TUR","UGA","VEN"],"klimatologie":["LIE"],"kreuze":["ETH","LIE"],"kamembe":["RWA"],"kfhkigali":["RWA"],"kgali":["RWA"],"kinigi":["RWA"],"kiyovu":["RWA"],"kolonne":["RWA"],"komplette":["RWA","ZWE"],"konfiskeret":["EGY","MAR","RWA","TUN"],"konfiskering":["RWA"],"kontrolposter":["RWA","UKR"],"kostenlosen":["GNB","NOR","RWA","TZA"],"kamerasystem":["MKD"],"kombi":["BWA","MKD","ZWE"],"kopfhorer":["MKD"],"kabwe":["ZMB"],"kafue":["ZMB"],"kariba":["ZMB","ZWE"],"karteneingabe":["ZMB"],"kaza":["ZMB","ZWE"],"kazungula":["ZMB","ZWE"],"kitwe":["ZMB"],"kombinationsimpfstoff":["SDN","TZA","ZMB"],"kontamination":["ZMB"],"konzentrieren":["SLE","UKR","ZMB"],"kopfe":["ZMB"],"kostenfrei":["BRN","COG","MDV","TGO","ZMB"],"kraftstoffknappheit":["ETH","ZMB"],"kraftstoffreserven":["ZMB"],"kreditkartenkonto":["PAN","ZMB"],"kreditkartenzahlungen":["MDA","MEX","ZMB"],"kupfergurtel":["ZMB"],"kursen":["ZMB"],"kwame":["ZMB"],"kangaroo":["AUS"],"kanguru":["AUS"],"karama":["AUS"],"kardiotoxischen":["AUS"],"kaskoversicherung":["ARM","AUS","EGY","URY"],"kavanagh":["AUS"],"klebenden":["AUS"],"klonen":["AUS","BRA","GTM"],"kompensation":["AUS"],"konditionen":["AUS","LBN"],"kontaminiertem":["AUS"],"koperscannern":["AUS"],"korperscanner":["AUS"],"kreislaufsymptome":["AUS"],"krokodile":["AUS","BRN"],"krokodiller":["AUS"],"krydser":["AUS","GEO"],"kulturell":["AUS"],"kuhl":["BTN","ETH","PER","USA","VEN"],"kaimaninseln":["GBR"],"kanalinseln":["GBR"],"kapstadt":["GBR","ZAF"],"karibik":["BHS","CUB","FRA","GBR","GTM","TTO","USA","VEN"],"karibischen":["COL","FRA","GBR","NIC","PAN"],"kingdomconsular":["GBR"],"kingdomtelephone":["GBR"],"kingdomx":["GBR"],"klassenreise":["GBR"],"klassenreisen":["GBR"],"klingen":["GBR"],"knightsbridge":["GBR"],"kommende":["CUB","GBR","NZL","RUS","TUR"],"kommunikationsnetzen":["GBR"],"konsularisch":["COG","EGY","GBR"],"kakaomap":["KOR"],"kase":["AND","KOR","MLT"],"klauenseuche":["GTM","KOR","MNG"],"kontaktinfo":["KOR"],"kontaktoplysninger":["KOR"],"korail":["KOR"],"koreansk":["KOR"],"kostenpflichtig":["KOR","LKA"],"krankheitssymptome":["KOR"],"kreditinstitute":["KOR"],"krisenubungen":["KOR"],"kalenderjahre":["GRC","IRN"],"kenland":["GRC"],"kentro":["GRC"],"klagen":["GRC"],"klth":["GRC"],"knosou":["GRC"],"knuckleduster":["GRC","HKG"],"kommerziell":["GRC"],"kooperation":["CPV","GRC"],"kostenintensive":["GRC"],"kountouriotou":["GRC"],"kustenstreifen":["COL","GRC"],"kapazitatsgrenzen":["CHN"],"karakoram":["CHN","PAK"],"kashgar":["CHN"],"kaufbelege":["CHN"],"khunjerab":["CHN","PAK"],"kina":["CHN","PNG"],"kinesisk":["CHN"],"kinesiske":["CHN"],"klinikzentren":["CHN"],"kommuniziert":["CHN","VNM"],"kong":["CHN","HKG","KHM","MAC","TGO"],"kopiert":["BRA","CHN","HKG","THA","VNM"],"korpertemperatur":["CHN","KEN"],"kosmetische":["CHN"],"krankenversorgung":["CHN"],"kreditkartenabrechnungen":["CHN","TZA"],"kulturamte":["CHN"],"kunststoffbehalter":["CHN"],"kwong":["CHN"],"kystomrader":["CHN","KEN","VNM"],"kalash":["PAK"],"kameez":["PAK"],"karachi":["PAK"],"karak":["JOR","PAK"],"karakorum":["PAK"],"karatschi":["PAK"],"kartarpur":["PAK"],"kaschmirregion":["PAK"],"keamari":["PAK"],"khan":["KEN","KHM","MNG","PAK","THA"],"khyber":["PAK"],"kidnapperne":["COL","MEX","NGA","PAK","PHL"],"kirchen":["CHL","IDN","KWT","NGA","PAK","THA","UKR"],"kleinfluggeraten":["PAK"],"kleinflugkorper":["PAK"],"knappe":["PAK"],"koalitionsregierung":["PAK"],"kohat":["PAK"],"kontext":["AZE","COL","EGY","IDN","IRQ","PAK","SLE","TUN"],"kontrolleret":["PAK"],"kontrollinje":["PAK"],"koordiniert":["HTI","PAK"],"kopfschmerz":["BOL","ECU","PAK","PER"],"korangi":["PAK"],"kortvarige":["COL","JPN","MEX","NGA","PAK","PER"],"kunstlern":["PAK"],"kurram":["PAK"],"kamensko":["BIH"],"kamenso":["BIH"],"karakaj":["BIH"],"kautionshinterlegung":["BIH"],"kladusa":["BIH"],"kleinerer":["BIH","COD","KEN","PER"],"kohlebefeuerung":["BIH"],"konvertible":["BIH"],"kosevo":["BIH"],"kabardino":["GEO","RUS"],"kalkulieren":["COL","DZA","NZL","RUS"],"kamchatka":["RUS"],"kamtjatka":["RUS"],"kamtschatka":["RUS"],"karachai":["RUS"],"karachayevo":["RUS"],"kartendienstleistern":["ALB","RUS"],"khabarovsk":["RUS"],"kleinste":["NIC","NOR","RUS"],"kolobovskiy":["RUS"],"kommunikationsdienste":["IRN","NIC","RUS"],"koncert":["RUS"],"konfliktgebiete":["RUS"],"konigsberg":["RUS"],"konrad":["RUS"],"konsekvenser":["RUS"],"kontaktverbote":["RUS"],"kontaminationen":["RUS"],"kosmetika":["PER","RUS","TZA"],"kostenpflichtigen":["CUB","PER","RUS"],"koursk":["RUS"],"kraftstoffausgabe":["RUS"],"kraftstoffversorgung":["RUS"],"krai":["RUS"],"krankheitsfalle":["PNG","RUS"],"krasnaya":["RUS"],"krasnodar":["RUS"],"krasnogo":["RUS"],"krasnogorsk":["RUS"],"kredite":["RUS"],"kreisverwaltungen":["RUS"],"krigen":["RUS"],"krigshandlinger":["RUS","UKR"],"kroku":["RUS"],"kruglovka":["RUS"],"kulturgut":["ARM","CUB","RUS"],"kummern":["PER","RUS","TUR"],"kunichina":["RUS"],"kunstgegenstanden":["ARM","COD","NGA","RUS"],"kuril":["RUS"],"kurilen":["RUS"],"kurilerne":["RUS"],"kursk":["RUS"],"klassifizierung":["GNB"],"kustengebiete":["BHR","GNB"],"kogo":["GNQ"],"kontrollpunkte":["GNQ","MDA","TJK","UKR"],"kriege":["GNQ","IRN"],"keinerlei":["BHS","CUB","DOM","ETH"],"klonari":["BHS"],"kokain":["BGD","HKG","PER"],"kongconsulate":["HKG","MAC"],"kongpostal":["HKG","MAC"],"kongtelephone":["HKG","MAC"],"kabylie":["DZA"],"kalkulierbar":["DZA"],"kamelture":["DZA","JOR"],"kantara":["DZA"],"khalef":["DZA"],"khelifa":["DZA"],"khenchela":["DZA"],"kkede":["DZA","EGY","IDN","TUN"],"knappen":["DZA"],"konsulater":["DZA"],"kontaminierter":["DZA"],"ksar":["DZA","TUN"],"kaabong":["UGA"],"kalerwe":["UGA"],"kamen":["BGD","GHA","IRN","NIC","PHL","SAU","UGA"],"kamwenge":["UGA"],"kanugu":["UGA"],"karamoja":["UGA"],"kasese":["UGA"],"kate":["UGA"],"kibale":["UGA"],"kidepo":["UGA"],"kisoro":["UGA"],"kitagoma":["UGA"],"kitchen":["UGA","USA"],"knallerter":["KHM","UGA"],"kolonialzeit":["SLE","UGA"],"komamboga":["UGA"],"kongolesischen":["COD","COG","UGA"],"konzerten":["UGA"],"kotido":["UGA"],"kreuzungsbereich":["UGA"],"kyabandara":["UGA"],"kyegegwa":["UGA"],"kyoga":["UGA"],"korperverletzung":["BRB","KEN"],"karosserie":["AGO","TZA"],"katyavala":["AGO"],"konsulate":["AGO","TUR","USA"],"korrekten":["AGO"],"kurzzeitbesucher":["AGO"],"kwanza":["AGO"],"kiosken":["ARG"],"klimatisierte":["ARG","URY"],"kommend":["ARG","BRA","ECU","JOR","NOR","PAN","PER","SGP","XKX","ZWE"],"kommissariat":["ARG","TCD"],"konsularabteilung":["ARG","AZE","GEO","KGZ","TJK","UKR","ZWE"],"krankenhausaufenthalte":["ARG"],"kartenbetrugsrisiko":["BRA"],"kartendaten":["BRA","KHM"],"kartenleseterminal":["BRA"],"kartenterminal":["BRA"],"katalog":["BRA","TZA"],"kathedrale":["BRA"],"keys":["BRA"],"klassen":["BRA"],"kleidungswechsel":["BRA"],"konferenzen":["BRA","LKA"],"konsularbeamten":["BRA"],"kontrollierte":["BRA","HTI","TCD"],"kreditkartenabbuchungen":["BRA"],"kunstlerisch":["BRA"],"kunstlerwettbewerben":["BRA"],"kaeo":["KHM"],"kambodscha":["KHM","LAO","THA"],"kambodschanische":["KHM"],"kambodschanischen":["KHM","LAO"],"kambodschanischer":["KHM"],"kampong":["BRN","KHM"],"kampot":["KHM"],"kandal":["KHM"],"kang":["KHM"],"keng":["KHM"],"kennzeichnungen":["KHM"],"khao":["KHM","LAO","THA"],"khmemarak":["KHM"],"khmer":["KHM"],"khmersoviethospital":["KHM"],"kiem":["KHM","LAO","VNM"],"kien":["KHM"],"klongtoey":["KHM","THA"],"knicke":["KHM"],"knowlesi":["IDN","KHM","LAO","PHL","THA","VNM"],"kombinationspraparate":["KHM"],"konigsfamilie":["KHM"],"konigshau":["KHM","THA"],"konstitutionelle":["KHM","THA"],"kontorer":["KHM"],"krabey":["KHM","LAO","THA"],"kraftfahrzeugverkehr":["KHM"],"krankheitsbild":["KHM","LAO"],"kratie":["KHM"],"krolar":["KHM"],"krong":["KHM"],"krydsild":["COL","KHM","MEX"],"kulen":["KHM"],"kulturguter":["GEO","KHM","MAR","PER","UKR"],"kulturtourismu":["KHM"],"kurzzeittouristen":["KHM"],"kwai":["KHM","LAO","THA"],"karavostasi":["CYP"],"kaskoschaden":["CYP"],"katalanou":["CYP"],"kato":["CYP"],"kreislaufbelastung":["CYP"],"kanadische":["CAN"],"kanadischem":["CAN"],"kanadischen":["CAN","HTI"],"kanadischer":["CAN"],"konsulter":["CAN"],"kontaktl":["CAN"],"korperlicher":["CAN","GHA","SAU"],"kortskimmere":["CAN"],"krankenhause":["CAN","TUR"],"kustenprovinzen":["CAN"],"kabo":["CAF"],"kampfe":["CAF"],"kampfen":["CAF","ETH","LBN","MLI"],"kinshasa":["CAF","COD","COG"],"knochen":["CAF"],"komitee":["CAF"],"konfliktgeschehen":["CAF","SYR"],"kreuz":["CAF"],"kinderraub":["GTM"],"klauseln":["GTM"],"kontobewegungen":["GTM"],"koordinierten":["GTM"],"kreuzfahrtschiffe":["GTM","TTO"],"kreuzfeuer":["GTM","MEX"],"kurzwahl":["GTM","LKA"],"kaloum":["GIN"],"kankan":["GIN"],"kindia":["GIN"],"kissidougou":["GIN"],"koyama":["GIN"],"krisenhaften":["GIN"],"kehren":["HTI","JOR","SYC"],"kenscoff":["HTI"],"kreol":["HTI"],"kreyol":["HTI"],"kriminalitatsniveau":["HTI"],"konan":["CIV"],"korogho":["CIV"],"kalteeinbruche":["KGZ"],"kara":["KGZ"],"karakol":["KGZ"],"kgembassy":["KGZ"],"khorog":["KGZ","TJK"],"kievskaia":["KGZ"],"kirghizistan":["KGZ"],"kirgisisch":["KGZ"],"kirgisische":["KGZ"],"kirgisischen":["KGZ"],"kirgisischer":["KGZ"],"kirgui":["KGZ","TJK"],"kirguisa":["KGZ","TJK"],"kirguiso":["KGZ"],"kraftstoffverbrauch":["KGZ"],"krivonosov":["KGZ"],"kyrgystan":["KGZ","UZB"],"kyrgyz":["KGZ","TJK","UZB"],"kyrgyzstani":["KGZ"],"kyzyl":["KGZ"],"kabuki":["JPN"],"kabukicho":["JPN"],"kamiyacho":["JPN"],"kamiyama":["JPN"],"kansai":["JPN"],"kanto":["JPN"],"kasama":["JPN"],"katastrofevarslinger":["JPN"],"katsurao":["JPN"],"kaugummi":["JPN","MDV","SGP"],"kernkraftwerk":["JPN"],"kinki":["JPN"],"kioto":["JPN"],"kita":["IDN","JPN","MLI"],"koban":["JPN"],"kojimachi":["JPN"],"koshin":["JPN"],"krisenvorsorge":["BOL","CUB","EGY","JPN","MEX","TZA","XKX"],"kuchinoerabu":["JPN"],"kundenfanger":["JPN"],"kusatsu":["JPN"],"kyakuhiki":["JPN"],"kyushu":["JPN"],"kreditkarteneinsatz":["MDA"],"keita":["MLI"],"kenieroba":["MLI"],"kenioroba":["MLI"],"keye":["MLI"],"kidal":["MLI"],"koordinierte":["MLI"],"koulikoro":["MLI","NER"],"koulikouro":["MLI"],"koutiala":["MLI"],"kraftwerke":["MLI"],"kreditkartenbetrugereien":["MLI"],"krankheitsbilder":["ECU","SYC","TUV"],"kenzi":["MAR"],"ketama":["MAR"],"kulturelle":["COD","CUB","FSM","MAR","SGP"],"kvinde":["MAR"],"kajakfahrten":["MNG"],"kanu":["MNG"],"kaufhausern":["MNG"],"khaan":["MNG"],"khandgait":["MNG"],"khankh":["MNG"],"khiagt":["MNG"],"khoroo":["MNG"],"khovd":["MNG"],"khuvsgul":["MNG"],"kindesentfuhrung":["MNG"],"kleinfahrzeuge":["MNG"],"kakhovka":["UKR"],"kamphandlinger":["TUR","UKR"],"kassieren":["UKR"],"kerch":["UKR"],"kernreaktorunfall":["UKR"],"kharkiv":["UKR"],"kherson":["UKR"],"kiev":["UKR"],"klovska":["UKR"],"klovsky":["UKR"],"konfliktregionen":["COL","GEO","SDN","UKR"],"konsularservice":["UKR"],"kontakter":["UKR"],"kontoauszuge":["FJI","UKR"],"kontraktova":["UKR"],"kontrolldatum":["UKR"],"kontrollpunkt":["UKR"],"korallen":["EGY","JOR","KEN","MEX","MHL","PLW","UKR"],"korruption":["ETH","IRN","PNG","UKR"],"kostelna":["UKR"],"kreditkartenabrechnung":["UKR"],"krigsm":["UKR"],"kriminalitatsrisiko":["UKR"],"kritisk":["UKR"],"krywy":["UKR"],"kulturerrungenschaften":["UKR"],"kunst":["ALB","UKR"],"kunstlerische":["UKR"],"kyiv":["UKR"],"kyivstar":["UKR"],"kyjiw":["UKR"],"kaka":["NZL"],"kaninchen":["NZL"],"killer":["CUB","NZL"],"kiwi":["NZL"],"kiwiacces":["NZL"],"karakalkpakstan":["UZB"],"karakalpakstan":["UZB"],"kashkadarya":["UZB"],"khojib":["UZB"],"khorezm":["UZB"],"khos":["UZB"],"kibray":["UZB"],"korperpiercing":["EGY","UZB"],"kolumbien":["COL","CRI","ECU","PAN","PER","PRY","VEN"],"kailahun":["SLE"],"kaufkraftverluste":["SLE"],"keke":["LBR","SLE"],"khallow":["SLE"],"kissy":["SLE"],"kommunalwahlen":["BEN","SLE"],"krio":["SLE"],"karima":["SDN"],"kasala":["SDN"],"kassala":["SDN"],"khartoum":["SDN"],"khartum":["SDN"],"khatim":["SDN"],"kopfbedeckung":["SDN","ZAF"],"kordofan":["SDN"],"kampfern":["IRQ","SOM"],"kismayo":["SOM"],"kriegsschiffen":["SOM"],"kanem":["TCD"],"karal":["TCD"],"kebbi":["NGA","TCD"],"kerim":["TCD"],"klemat":["TCD"],"kommunikationsmitteln":["TCD"],"konstituierung":["TCD"],"kunsthandwerklichen":["TCD"],"kalaikum":["TJK"],"kalinin":["TJK"],"kamarob":["TJK"],"karabaeva":["TJK"],"karaboev":["TJK"],"khatlon":["TJK"],"khodjend":["TJK"],"khojand":["TJK"],"khujand":["TJK"],"kulyab":["TJK"],"kumsangir":["TJK"],"kamel":["TUN"],"kampen":["TUN"],"kantaoui":["TUN"],"kasserine":["TUN"],"kaufe":["TUN"],"kerkennah":["TUN"],"kompetenzen":["TUN"],"kreditkartenkriminalitat":["TUN"],"kabinen":["URY"],"kennnummer":["URY"],"komplexe":["URY"],"kapitalverbrechen":["NIC"],"karibikregion":["NIC"],"katholische":["NIC","TUR"],"kostenfrage":["NIC"],"kursverlusten":["NIC"],"kurzaufenthalten":["NIC","USA"],"kanalisation":["ARM","AZE","LBR"],"kunsthandwerksmarkte":["LBR"],"kayi":["COG"],"kindamba":["COG"],"kinkala":["COG"],"kleinstvertretung":["COG"],"klinischen":["COG"],"keran":["TGO"],"korbongou":["TGO"],"kpendjal":["TGO"],"kummert":["TGO"],"kartenformat":["MUS","XKX"],"kino":["MUS","THA"],"kitesurf":["MUS"],"konservative":["BRN","MUS","NIU"],"kesington":["KNA"],"kittian":["KNA"],"kameraausrustung":["SYC"],"krankenrucktransport":["SYC"],"kalba":["GHA"],"kintampo":["GHA"],"kleinbussen":["GHA","TZA"],"kofi":["GHA"],"kokrobite":["GHA"],"korle":["GHA"],"kostengunstige":["GHA","MEX"],"kotoka":["GHA"],"kumasi":["GHA"],"kurse":["GHA","LBN"],"kapazitat":["CUB"],"kartenzahlungssystem":["CUB"],"keroseno":["CUB"],"kerzen":["CUB"],"klimatisierung":["CUB"],"knappheit":["CUB"],"konvertibler":["CUB"],"konvertierbarer":["CUB"],"korperverletzungen":["CUB"],"krankenrucktransporten":["CUB"],"krankhausern":["CUB"],"kratzverletzungen":["CUB","GEO","OMN"],"kuba":["CUB","USA"],"kubaaufenthalt":["CUB"],"kubanische":["CUB","USA"],"kubanischen":["CUB"],"kubanischer":["CUB"],"kubareisende":["CUB","USA"],"kajetia":["GEO"],"kakhetia":["GEO"],"kampfhunde":["GEO","TUR"],"kapazitatsbedingte":["GEO"],"karabaj":["AZE","GEO"],"karachay":["GEO"],"kartli":["GEO"],"kazbegi":["GEO"],"kent":["GEO"],"kleinkindern":["GEO"],"klosterkomplex":["GEO"],"korte":["GEO"],"kostava":["GEO"],"krieg":["GEO","LAO","PHL"],"kunstdrucke":["GEO"],"kurzzeitaufenthalten":["GEO"],"kutaisi":["GEO"],"kvemo":["GEO"],"karbala":["IRQ"],"karkh":["IRQ"],"karrada":["IRQ"],"kataib":["IRQ"],"kheir":["IRQ","JOR"],"kirkuk":["IRQ"],"koya":["IRQ"],"kraften":["IRQ"],"kriminellem":["IRQ"],"kulturgutergesetz":["IRQ"],"kurdischen":["IRQ","TUR"],"kurdish":["IRN","IRQ"],"kurdistan":["IRN","IRQ","TUR"],"kuwait":["BHR","IRQ","KWT","QAT"],"kandidaten":["COL"],"karibische":["COL"],"karteneinschub":["COL"],"kollateralschaden":["COL"],"kolumbianische":["COL"],"kolumbianischen":["COL","VEN"],"kommenden":["COL"],"kongresse":["COL"],"kordilleren":["COL"],"kurzzeitentfuhrung":["COL"],"kyst":["COL","KEN"],"kamelmilch":["ARE"],"keffiyeh":["ARE"],"khaleej":["ARE"],"kindesentziehungen":["ARE"],"koalition":["ARE"],"kommentaren":["ARE","EGY"],"kreuzfahrt":["ARE","TTO"],"koweit":["KWT"],"kustenbereichen":["EGY","KWT"],"kuwaitappointment":["KWT"],"kuwaitcity":["KWT"],"kuwaiti":["KWT"],"kuwaitie":["KWT"],"kuwaitische":["KWT"],"kuwaitischen":["KWT"],"kuwaitischer":["KWT"],"kuwaitpostal":["KWT"],"kuwaittelephone":["KWT"],"kaki":["SAU"],"khafji":["SAU"],"khali":["OMN","SAU"],"khobar":["SAU"],"kleidungsstucke":["BRN","LKA","SAU"],"knie":["BRN","LKA","SAU"],"knivoverfald":["SAU"],"kodifiziert":["SAU"],"koncerter":["FRA","SAU"],"kongefamilie":["SAU"],"kontrollierter":["PLW","SAU"],"konvertere":["EGY","SAU"],"konvertierbaren":["SAU"],"koranen":["SAU"],"kritisere":["SAU"],"ksaembassye":["SAU"],"katar":["QAT"],"katarische":["QAT"],"katarischen":["QAT"],"katarischer":["QAT"],"kontaktnummern":["QAT"],"karbabad":["BHR"],"karzakan":["BHR"],"kabir":["OMN"],"khalid":["OMN"],"kultstatte":["OMN"],"kausale":["IDN","TLS"],"kave":["TLS"],"konfliktpotential":["TLS"],"kupang":["TLS"],"kahuzi":["COD"],"kamina":["COD"],"katanga":["COD"],"katastrophen":["COD","ESP"],"kavuma":["COD"],"kenge":["COD"],"kikwit":["COD"],"kimbanseke":["COD"],"kisangani":["COD"],"kongolesische":["COD"],"konsulaten":["COD","TUR"],"kuluna":["COD"],"kwamouth":["COD"],"kwango":["COD"],"kwilu":["COD"],"kirche":["SYR","TUR"],"kobane":["SYR"],"konig":["LBY","SYR","THA"],"kustenzone":["SYR"],"kawran":["BGD"],"khagrachari":["BGD"],"khulna":["BGD"],"konservativeren":["BGD"],"konstituiert":["BGD"],"kaftoun":["LBN"],"kalamoun":["LBN"],"kamphandlingerne":["LBN"],"khaled":["EGY","LBN"],"khandak":["LBN"],"kkelig":["LBN"],"kobayter":["LBN"],"konfessionell":["LBN"],"konfliktphasen":["LBN"],"konomiske":["LBN"],"konservativ":["BOL","CRI","LBN","XKX"],"kopimedicin":["LBN"],"kors":["LBN"],"koura":["LBN"],"kousba":["LBN"],"krisesituation":["LBN"],"kugler":["LBN"],"kaen":["LAO"],"kartenspiel":["LAO"],"khon":["LAO"],"khonkaen":["LAO"],"khouang":["LAO"],"khoun":["LAO"],"kloster":["LAO"],"konsumenten":["LAO"],"kontaminieren":["LAO"],"kostenloser":["LAO"],"kreisen":["LAO"],"kalouti":["JOR"],"khalidi":["JOR"],"kizkulesi":["AZE","JOR"],"kontantbel":["JOR"],"krisen":["JOR"],"kavaliersdelikt":["DOM"],"kostenubernahmeerklarung":["DOM"],"krisenreaktionszentrum":["DOM"],"kanalzone":["PAN"],"kilometern":["PAN"],"konfliktsituationen":["PAN"],"kreditkartenkontoauszug":["PAN"],"kreuzfahrtschiff":["PAN"],"kreuzfahrtterminal":["PAN","PER"],"kamla":["TTO"],"karibikinsel":["TTO"],"kauflicher":["TTO"],"konsumiert":["DJI","FSM","TTO"],"kabinebzw":["CRI"],"kaffee":["AND","CRI","ETH","TUR"],"kartenausstellende":["CRI"],"katastrophengebiete":["CRI"],"kindersitz":["CRI"],"kindersitze":["CRI"],"kommission":["CRI","TZA","ZWE"],"konserven":["CRI","PNG"],"konsularinfo":["CRI"],"kakteen":["MEX"],"kartellerne":["MEX"],"kartellfuhrer":["MEX"],"kartenanbieter":["MEX"],"kender":["MEX","PHL","ZAF"],"kontaktnummer":["MEX"],"krater":["MEX"],"kreditrahmen":["MDV","MEX"],"kukulcan":["MEX"],"kukulkan":["MEX"],"kulturweit":["MEX"],"kiwibank":["NIU"],"kostspielige":["NIU","PNG"],"kolonia":["FSM"],"kosrae":["FSM"],"kunstler":["FSM","PHL"],"konten":["FJI"],"kurvenreichen":["FJI","NOR"],"kangava":["SLB"],"kapazitaten":["SLB","VEN"],"kastom":["SLB"],"kombito":["SLB"],"kongalai":["SLB"],"krisenhafter":["SLB"],"kukum":["SLB"],"koror":["PLW"],"kadovar":["PNG"],"kainantu":["PNG"],"ketten":["BEN","PNG"],"kimbe":["PNG"],"kokoda":["PNG"],"konfliktzone":["PNG"],"kundu":["PNG"],"kustenschiffe":["PNG"],"kustenschiffen":["PNG"],"kalanka":["MLT"],"kapunata":["MLT"],"karm":["MLT"],"kartengebende":["MLT"],"kennt":["MLT","PHL"],"konvertiblen":["MLT"],"kagera":["TZA"],"kariakoo":["TZA"],"kigoma":["TZA"],"kilimandscharo":["TZA"],"kilimanjaro":["TZA"],"kisiju":["TZA"],"kitaya":["TZA"],"korperkontrolle":["TZA"],"kustenstadte":["TZA"],"kartendienste":["ALB"],"kombit":["ALB"],"kulturschatzen":["ALB"],"kamerazubehor":["PER"],"kendt":["PER"],"kleinflugzeuge":["PER"],"kompliziert":["PER"],"kostspielig":["PER"],"kuelap":["PER"],"kurier":["PER"],"kalugtan":["PHL"],"kalye":["PHL"],"kampagne":["PHL"],"kanlaon":["PHL"],"kasambagan":["PHL"],"katedral":["PHL"],"keuchhusten":["PHL"],"kidapawan":["PHL"],"kilogramo":["PHL"],"koste":["PHL"],"kreditkartengesellschaft":["PHL"],"kudarat":["PHL"],"kfor":["XKX"],"korperbedeckender":["XKX"],"kosovan":["XKX"],"krankheitsbildern":["MNE","XKX"],"kaleyfan":["MDV"],"kandima":["MDV"],"kandolu":["MDV"],"kauen":["MDV"],"kuramathi":["MDV"],"kuredu":["MDV"],"kramer":["MHL"],"khor":["DJI"],"kirchliche":["DJI","KEN"],"klimawandel":["DJI","LKA"],"kontingent":["DJI"],"kassem":["IRN"],"kerman":["IRN"],"kermanshah":["IRN"],"khomeini":["IRN"],"khuzestan":["IRN"],"kish":["IRN"],"kleidungsvorschriften":["IRN"],"kleru":["IRN"],"knocheln":["IRN"],"kommentieren":["IRN","TUR"],"kommunikationswege":["IRN"],"kopftuch":["IRN"],"korperformen":["IRN"],"kraftfahrer":["IRN","TKM"],"kulturerbe":["IRN"],"kurden":["IRN"],"kurdische":["IRN","TUR"],"khamsim":["EGY"],"kharga":["EGY"],"kite":["CPV","EGY"],"kommentare":["EGY","TUR"],"komplikation":["EGY"],"koptische":["EGY"],"kostenfreie":["EGY"],"kritischen":["EGY"],"kustenabschnitt":["EGY"],"kutyme":["EGY"],"kysterne":["EGY","ZAF"],"komercijalna":["MNE"],"kotor":["MNE"],"kovac":["MNE"],"kratzer":["MNE"],"kucnih":["MNE"],"kantonen":["ECU"],"kriterium":["ECU"],"kundschaft":["ECU"],"kustengebiet":["ECU","LBY"],"kustengegend":["ECU"],"kakuma":["KEN"],"kasarani":["KEN"],"kcaa":["KEN"],"keniana":["KEN"],"kenianische":["KEN"],"kenianischen":["KEN"],"keniano":["KEN"],"kenyaembassyspain":["KEN"],"kenyansk":["KEN"],"kenyanske":["KEN"],"kerio":["KEN"],"kfcb":["KEN"],"kibera":["KEN"],"kilifi":["KEN"],"kirisia":["KEN"],"kisumu":["KEN"],"klassifiziert":["KEN"],"kustenprovinz":["KEN"],"kwale":["KEN"],"konkurrenz":["LBY"],"kufrah":["LBY"],"kalku":["LVA"],"karina":["LVA"],"kibilde":["LVA"],"kliniska":["LVA"],"kukaini":["LVA"],"kombinationen":["SGP"],"kugelsichere":["SGP"],"kalahari":["BWA"],"karteneinfuhrschlitz":["BWA"],"kasane":["BWA"],"kgalagadi":["BWA"],"kreditkartenraub":["BWA"],"kadiso":["ETH"],"kampe":["ETH"],"kebele":["ETH"],"kefle":["ETH"],"kelam":["ETH"],"kelem":["ETH"],"kellem":["ETH"],"kennzeichennummer":["ETH"],"kilbet":["ETH"],"kilder":["ETH"],"kilometraje":["ETH"],"konfrontationen":["ETH"],"konso":["ETH"],"kontaktperson":["ETH"],"korahe":["ETH"],"kraftstoffe":["ETH"],"kunsthistorischen":["ETH"],"kaprivi":["ZWE"],"karibabecken":["ZWE"],"kunsthandwerk":["ZWE"],"katabatic":["ATA"],"khoi":["VNM"],"khuong":["VNM"],"kinderbanden":["VNM"],"klebstoff":["VNM"],"klimaforskelle":["VNM"],"knew":["VNM"],"kontrollerer":["VNM"],"krankenhauspersonal":["VNM"],"kahramankazan":["TUR"],"kahramanmara":["TUR"],"kapikoy":["TUR"],"karanfil":["TUR"],"karkam":["TUR"],"katolske":["TUR"],"kaufgelegenheit":["TUR"],"kaufgelegenheiten":["TUR"],"kaufzwang":["TUR"],"kautionszahlungen":["TUR"],"kayseri":["TUR"],"kemal":["TUR"],"kendskab":["TUR"],"kili":["TUR"],"kimlik":["TUR"],"kolnisch":["TUR"],"korrekturen":["TUR"],"kortere":["TUR"],"kostenstrukturen":["TUR"],"kostenvoranschlage":["TUR"],"kostspieligen":["TUR"],"kulturel":["TUR"],"kumlu":["TUR"],"kurdenfrage":["TUR"],"kurdiske":["TUR"],"kurumu":["TUR"],"kaare":["NOR"],"keiser":["NOR"],"kirkene":["NOR"],"kluge":["NOR"],"kommunikationsgeraten":["NOR"],"kristiansand":["NOR"],"kyrre":["NOR"],"kyrrest":["NOR"],"kleinflugzeugen":["VEN"],"kontrolleuren":["VEN"],"klingenlange":["CPV"],"kopfstein":["CPV"],"kandy":["LKA"],"kilinochchi":["LKA"],"kirker":["LKA","NGA"],"kohle":["LKA"],"kraftstoffpreise":["BOL","LKA","TKM"],"kulturstatten":["LKA"],"kumaraswamy":["LKA"],"kalbajar":["AZE"],"karabach":["ARM","AZE"],"karabagh":["AZE"],"karabakh":["ARM","AZE"],"kaukasusgebiet":["AZE"],"kaviar":["AZE"],"kelbajar":["AZE"],"khankendi":["AZE"],"khojali":["AZE"],"khojavand":["AZE"],"kachia":["NGA"],"kaduna":["NGA"],"kainji":["NGA"],"kano":["NER","NGA"],"kastration":["NGA"],"katsina":["NGA"],"kofo":["BEN","NGA"],"kogi":["NGA"],"kpodji":["NGA"],"kuje":["NGA"],"kwali":["NGA"],"kwara":["NGA"],"kaspische":["TKM"],"konsulargebuhr":["TKM"],"kuschka":["TKM"],"khumbi":["SWZ"],"kuhen":["SWZ"],"kondensmilch":["AND"],"kurtaxe":["AND"],"kalale":["BEN"],"kandi":["BEN"],"kerou":["BEN"],"koakrana":["BEN"],"konkombri":["BEN"],"kultstatten":["BEN"],"kapprovinz":["ZAF"],"kapregion":["ZAF"],"keime":["ZAF"],"kendte":["ZAF"],"khayelitsha":["ZAF"],"kontaktdetail":["ZAF"],"kooperieren":["ZAF"],"korruptionshotline":["ZAF"],"kortterminalen":["ZAF"],"kraftige":["ZAF"],"kreuzung":["FRA","USA","ZAF"],"kruger":["ZAF"],"kruguer":["ZAF"],"kuhlem":["ZAF"],"kund":["ZAF"],"kurzzeitentfuhrungen":["ZAF"],"kwazulu":["ZAF"],"kellner":["LSO"],"kingsway":["LSO"],"koffi":["LSO"],"konigliche":["LSO"],"kalifornien":["USA"],"kansa":["USA"],"keane":["USA"],"kentucky":["USA"],"kern":["USA"],"kilauea":["USA"],"kinderpornographie":["USA"],"kofferschlos":["USA"],"konzentrationen":["USA"],"kubanisch":["USA"],"kubareise":["USA"],"kunftigen":["USA"],"kurzeste":["USA"],"kustenraum":["USA"],"karibikinseln":["FRA"],"kennzeichnen":["FRA"],"kleinstfahrzeugen":["FRA"],"konsuln":["FRA"],"korsika":["FRA"],"kourou":["FRA"],"kraftradern":["FRA","IDN"],"kreisverkehrahnlichen":["FRA"],"kreisverkehrsahnlichen":["FRA"],"kreuzform":["FRA"],"kupon":["FRA"],"kaew":["THA"],"kamphaeng":["THA"],"kanchanaburi":["THA"],"karteneingabeschlitz":["THA"],"kaskoversichert":["THA"],"kavaliersdelikte":["THA"],"khiri":["THA"],"kilogram":["THA"],"klang":["THA"],"kleptomanie":["THA"],"knowledgeable":["THA"],"koniglichen":["THA"],"korrupten":["THA"],"korrupter":["THA"],"krabi":["THA"],"kriminalisiert":["THA"],"krokodil":["THA"],"kumulativ":["THA"],"klimakrise":["NER"],"knapper":["NER"],"koira":["NER"],"kommissariaten":["NER"],"kouara":["NER"],"koutoukale":["NER"],"kanaren":["ESP"],"kanarischen":["ESP"],"kanariske":["ESP"],"katalonien":["ESP"],"kraftfahrzeugbehorde":["ESP"],"kajaolalido":["IDN"],"kalimantan":["IDN"],"karangetang":["IDN"],"karno":["IDN"],"karo":["IDN"],"kasko":["IDN"],"kbri":["IDN"],"kedubesaustralia":["IDN"],"kelod":["IDN"],"kembar":["IDN"],"kemlu":["IDN"],"kerobokan":["IDN"],"kesehatan":["IDN"],"keterangan":["IDN"],"kibarer":["IDN"],"kitap":["IDN"],"klimaanlagen":["IDN"],"kobokan":["IDN"],"konservativer":["IDN"],"kontraindikationen":["IDN"],"koroway":["IDN"],"krakatau":["IDN"],"kualanamu":["IDN"],"kuningan":["IDN"],"kurzzeit":["IDN"],"kuta":["IDN"],"koran":["BRN"],"korperstrafe":["BRN"],"krokodilvorkommen":["BRN"],"kustennahen":["BRN"],"katari":["BOL"],"kapan":["ARM"],"karki":["ARM"],"karmrakar":["ARM"],"kornidzor":["ARM"],"korrekter":["ARM"],"korridor":["ARM"]}}